{"cluster_id": 12, "name": "BARRETT PAMELA KAYE REVOCABLE TRUST", "entity_count": 17, "parcel_count": 285, "total_market_value": 82684800, "total_acres": 182.3, "owner_names": ["BARRETT L CORP G P", "BARRETT M L LIMITED PARTNERSHIP", "BARRETT PAMEAL KAYE REVOCABLE TRUST", "BARRETT PAMELA KAY REVOCABLE TRUST", "BARRETT PAMELA KAYE REVOABLE TRUST", "BARRETT PAMELA KAYE REVOC TRUST ET AL", "BARRETT PAMELA KAYE REVOC TRUST ETAL", "BARRETT PAMELA KAYE REVOCABLE TRUST", "BARRETT PAMELA KAYE REVOCABLE TRUST ETAL", "BARRETT PAMELA KAYE REVOCBLE TRUST", "LAND ASSETTS RRL LLC", "M L BARRETT FAMILY LTD PARTNERSHIP", "M L BARRETT JR FAMILY LP", "M L BARRETT LIMITED PARTNERSHIP", "M LEE BARRETT JR CORP", "MLBJPBRRL LLC", "RIRALE FAMILY LIMITED PARTNERSHIP"], "registered_agents": [], "principal_offices": [], "primary_sos_status": "", "primary_foreign_state": "", "brand": "", "opencorporates": "https://opencorporates.com/companies?q=BARRETT+PAMELA+KAYE+REVOCABLE+TRUST&utf8=%E2%9C%93", "primary_type": "", "portfolio": {"n_parcels_with_acs": 262, "median_income": 73654, "median_home_value": 360121, "pct_renter": 52, "pct_poverty": null, "pct_vacant": 11, "pct_black": 20, "pct_white": 50, "pct_hispanic": 29, "pct_asian": 2}, "related": [{"owner": "BARRETT PAMELA KAYE REVOC TRUST ETAL", "parcels": 24, "via": "mailing address"}, {"owner": "LAND ASSETTS RRL LLC", "parcels": 3, "via": "mailing address"}, {"owner": "M L BARRETT LIMITED PARTNERSHIP", "parcels": 2, "via": "mailing address"}, {"owner": "BARRETT PAMELA KAYE REVOCBLE TRUST", "parcels": 1, "via": "mailing address"}, {"owner": "BARRETT PAMELA KAY REVOCABLE TRUST", "parcels": 1, "via": "mailing address"}, {"owner": "RIRALE FAMILY LIMITED PARTNERSHIP", "parcels": 1, "via": "mailing address"}, {"owner": "M L BARRETT FAMILY LTD PARTNERSHIP", "parcels": 1, "via": "mailing address"}, {"owner": "MLBJPBRRL LLC", "parcels": 1, "via": "mailing address"}, {"owner": "BARRETT PAMELA KAYE REVOC TRUST ET AL", "parcels": 1, "via": "mailing address"}, {"owner": "BARRETT M L LIMITED PARTNERSHIP", "parcels": 1, "via": "mailing address"}, {"owner": "M L BARRETT JR FAMILY LP", "parcels": 1, "via": "mailing address"}, {"owner": "BARRETT PAMEAL KAYE REVOCABLE TRUST", "parcels": 1, "via": "mailing address"}, {"owner": "M LEE BARRETT JR CORP", "parcels": 1, "via": "mailing address"}, {"owner": "BARRETT PAMELA KAYE REVOABLE TRUST", "parcels": 1, "via": "mailing address"}, {"owner": "BARRETT PAMELA KAYE REVOCABLE TRUST ETAL", "parcels": 1, "via": "mailing address"}, {"owner": "BARRETT L CORP G P", "parcels": 1, "via": "mailing address"}], "parcels": [{"parcel_id": "101440", "address": "1104 CAMPBELL ST", "lat": "36.189941", "lon": "-86.722451", "sale_price": -1.0, "sale_date": "", "market_value": 492700.0, "beds": 2.0, "bath": 1.0, "sqft": 1247.0, "year_built": "1973", "acres": 0.26}, {"parcel_id": "108291", "address": "2229 MAPLECREST DR", "lat": "36.177379", "lon": "-86.691576", "sale_price": -1.0, "sale_date": "", "market_value": 251500.0, "beds": 3.0, "bath": 1.0, "sqft": 1330.0, "year_built": "1952", "acres": 0.36}, {"parcel_id": "108490", "address": "2510 STINSON RD", "lat": "36.173148", "lon": "-86.677009", "sale_price": -1.0, "sale_date": "", "market_value": 241100.0, "beds": 2.0, "bath": 1.0, "sqft": 896.0, "year_built": "1945", "acres": 0.5}, {"parcel_id": "108933", "address": "2344 DENNYWOOD DR", "lat": "36.180216", "lon": "-86.683481", "sale_price": -1.0, "sale_date": "", "market_value": 287900.0, "beds": 3.0, "bath": 1.0, "sqft": 1272.0, "year_built": "1955", "acres": 0.29}, {"parcel_id": "108940", "address": "2404A DENNYWOOD DR", "lat": "36.179086", "lon": "-86.681881", "sale_price": -1.0, "sale_date": "", "market_value": 323600.0, "beds": 4.0, "bath": 2.0, "sqft": 1570.0, "year_built": "1958", "acres": 0.34}, {"parcel_id": "109878", "address": "3024 LEBANON PIKE", "lat": "36.175634", "lon": "-86.647698"}, {"parcel_id": "111363", "address": "3521 MAGNUM DR", "lat": "36.178768", "lon": "-86.612267", "sale_price": -1.0, "sale_date": "", "market_value": 290400.0, "beds": 4.0, "bath": 2.0, "sqft": 1612.0, "year_built": "1979", "acres": 0.19}, {"parcel_id": "115119", "address": "6107 PENNSYLVANIA AVE", "lat": "36.165048", "lon": "-86.862006", "sale_price": -1.0, "sale_date": "", "market_value": 227900.0, "beds": 2.0, "bath": 1.0, "sqft": 816.0, "year_built": "1930", "acres": 0.17}, {"parcel_id": "117213", "address": "1107 55TH AVE N", "lat": "36.160142", "lon": "-86.854541", "sale_price": -1.0, "sale_date": "", "market_value": 356100.0, "beds": 2.0, "bath": 2.0, "sqft": 1216.0, "year_built": "1930", "acres": 0.09}, {"parcel_id": "117301", "address": "1105 55TH AVE N", "lat": "36.16004", "lon": "-86.854533", "sale_price": -1.0, "sale_date": "", "market_value": 356100.0, "beds": 2.0, "bath": 2.0, "sqft": 1216.0, "year_built": "1930", "acres": 0.09}, {"parcel_id": "117302", "address": "1103 55TH AVE N", "lat": "36.159938", "lon": "-86.85453", "sale_price": -1.0, "sale_date": "", "market_value": 343000.0, "beds": 3.0, "bath": 1.0, "sqft": 1137.0, "year_built": "1951", "acres": 0.09}, {"parcel_id": "117303", "address": "1101 55TH AVE N", "lat": "36.159834", "lon": "-86.854523", "sale_price": -1.0, "sale_date": "", "market_value": 356100.0, "beds": 2.0, "bath": 2.0, "sqft": 1216.0, "year_built": "1930", "acres": 0.09}, {"parcel_id": "118374", "address": "1001 TRICE DR", "lat": "36.159172", "lon": "-86.859232", "sale_price": -1.0, "sale_date": "", "market_value": 219600.0, "beds": 2.0, "bath": 1.0, "sqft": 781.0, "year_built": "1955", "acres": 0.14}, {"parcel_id": "13686", "address": "4678 LICKTON PIKE", "lat": "36.280288", "lon": "-86.820785", "sale_price": -1.0, "sale_date": "", "market_value": 727400.0, "beds": 3.0, "bath": 1.0, "sqft": 2072.0, "year_built": "1900", "acres": 48.48}, {"parcel_id": "138360", "address": "1961 OMOHUNDRO DR", "lat": "36.15819", "lon": "-86.709063", "sale_price": -1.0, "sale_date": "", "market_value": 220300.0, "beds": 2.0, "bath": 1.0, "sqft": 832.0, "year_built": "1930", "acres": 0.29}, {"parcel_id": "138386", "address": "2513 WOODBERRY DR", "lat": "36.157456", "lon": "-86.678532", "sale_price": -1.0, "sale_date": "", "market_value": 293900.0, "beds": 3.0, "bath": 1.0, "sqft": 1025.0, "year_built": "1956", "acres": 0.33}, {"parcel_id": "139340", "address": "241A GRAYLYNN DR", "lat": "36.163422", "lon": "-86.676392", "sale_price": -1.0, "sale_date": "", "market_value": 307600.0, "beds": 2.0, "bath": 1.0, "sqft": 1070.0, "year_built": "1950", "acres": 0.64}, {"parcel_id": "139371", "address": "2211 LARIMORE DR", "lat": "36.156043", "lon": "-86.690829", "sale_price": -1.0, "sale_date": "", "market_value": 230400.0, "beds": 2.0, "bath": 1.0, "sqft": 925.0, "year_built": "1955", "acres": 0.51}, {"parcel_id": "139678", "address": "2831B LEBANON PIKE", "lat": "36.16638", "lon": "-86.660659", "sale_price": -1.0, "sale_date": "", "market_value": 271800.0, "beds": 2.0, "bath": 1.0, "sqft": 699.0, "year_built": "1931", "acres": 0.28}, {"parcel_id": "140451", "address": "2939 IRONWOOD DR", "lat": "36.160272", "lon": "-86.653252", "sale_price": -1.0, "sale_date": "", "market_value": 261100.0, "beds": 2.0, "bath": 1.0, "sqft": 1104.0, "year_built": "1954", "acres": 0.32}, {"parcel_id": "140870", "address": "2921 DUNMORE DR", "lat": "36.154425", "lon": "-86.656326", "sale_price": -1.0, "sale_date": "", "market_value": 307700.0, "beds": 3.0, "bath": 1.5, "sqft": 1350.36, "year_built": "1955", "acres": 0.32}, {"parcel_id": "141121", "address": "315 LORNA DR", "lat": "36.158897", "lon": "-86.669756", "sale_price": -1.0, "sale_date": "", "market_value": 316300.0, "beds": 2.0, "bath": 1.0, "sqft": 1333.0, "year_built": "1960", "acres": 0.33}, {"parcel_id": "141766", "address": "3220 CLOVERWOOD DR", "lat": "36.158005", "lon": "-86.642062", "sale_price": -1.0, "sale_date": "", "market_value": 347800.0, "beds": 3.0, "bath": 1.5, "sqft": 1672.0, "year_built": "1962", "acres": 0.26}, {"parcel_id": "142069", "address": "3403 LAUER DR", "lat": "36.158034", "lon": "-86.628399", "sale_price": -1.0, "sale_date": "", "market_value": 248800.0, "beds": 3.0, "bath": 1.0, "sqft": 1070.0, "year_built": "1967", "acres": 0.19}, {"parcel_id": "164258", "address": "1902 HILLSIDE AVE", "lat": "36.135211", "lon": "-86.783755", "sale_price": -1.0, "sale_date": "", "market_value": 268100.0, "beds": 1.0, "bath": 1.0, "sqft": 648.0, "year_built": "1925", "acres": 0.04}, {"parcel_id": "165060", "address": "118 RAINS AVE", "lat": "36.138688", "lon": "-86.763602", "sale_price": -1.0, "sale_date": "", "market_value": 574500.0, "beds": 9.0, "bath": 4.0, "sqft": 2845.0, "year_built": "1960", "acres": 0.23}, {"parcel_id": "165420", "address": "1806 STEWART PL", "lat": "36.134527", "lon": "-86.771175", "sale_price": -1.0, "sale_date": "", "market_value": 564300.0, "beds": 3.0, "bath": 1.0, "sqft": 1291.0, "year_built": "1940", "acres": 0.17}, {"parcel_id": "165990", "address": "0 WESTWOOD DR", "lat": "36.126006", "lon": "-86.775133", "sale_price": null, "sale_date": "", "market_value": null, "beds": null, "bath": 0.0, "sqft": null, "year_built": "", "acres": null}, {"parcel_id": "166085", "address": "603 CRAIGHEAD ST", "lat": "36.126423", "lon": "-86.774769", "sale_price": -1.0, "sale_date": "", "market_value": 659600.0, "beds": 0.0, "bath": 0.0, "sqft": 2880.0, "year_built": "1999", "acres": 0.18}, {"parcel_id": "166086", "address": "601 CRAIGHEAD ST", "lat": "36.12646", "lon": "-86.774494", "sale_price": -1.0, "sale_date": "", "market_value": 626800.0, "beds": 2.0, "bath": 1.0, "sqft": 684.0, "year_built": "1960", "acres": 0.14}, {"parcel_id": "166087", "address": "0 WHITE AVE", "lat": "36.126264", "lon": "-86.774579", "sale_price": null, "sale_date": "", "market_value": null, "beds": null, "bath": 0.0, "sqft": null, "year_built": "", "acres": null}, {"parcel_id": "167053", "address": "1984 LAVERGNE CT", "lat": "36.128745", "lon": "-86.73076", "sale_price": -1.0, "sale_date": "", "market_value": 317300.0, "beds": 2.0, "bath": 1.0, "sqft": 939.0, "year_built": "1950", "acres": 0.57}, {"parcel_id": "167160", "address": "415 BUNKERHILL DR", "lat": "36.130015", "lon": "-86.722961", "sale_price": 125000.0, "sale_date": "29 Oct 2013", "market_value": 391900.0, "beds": 3.0, "bath": 2.0, "sqft": 2088.0, "year_built": "1960", "acres": 0.7}, {"parcel_id": "167391", "address": "2015 ROSEMARY LN", "lat": "36.129211", "lon": "-86.750407", "sale_price": -1.0, "sale_date": "", "market_value": 268400.0, "beds": 2.0, "bath": 1.0, "sqft": 888.0, "year_built": "1950", "acres": 0.27}, {"parcel_id": "167397", "address": "2131 ROSEMARY LN", "lat": "36.127749", "lon": "-86.750486", "sale_price": -1.0, "sale_date": "", "market_value": 402800.0, "beds": 3.0, "bath": 2.0, "sqft": 1258.0, "year_built": "2000", "acres": 0.18}, {"parcel_id": "167404", "address": "409 FOOTHILL DR", "lat": "36.129309", "lon": "-86.72", "sale_price": -1.0, "sale_date": "", "market_value": 563800.0, "beds": 5.0, "bath": 3.0, "sqft": 2649.0, "year_built": "1960", "acres": 0.99}, {"parcel_id": "167493", "address": "2139 ROSEMARY LN", "lat": "36.127189", "lon": "-86.750553", "sale_price": -1.0, "sale_date": "", "market_value": 240900.0, "beds": 2.0, "bath": 1.0, "sqft": 756.0, "year_built": "1950", "acres": 0.17}, {"parcel_id": "167496", "address": "328 VIVELLE AVE", "lat": "36.126553", "lon": "-86.7517", "sale_price": -1.0, "sale_date": "", "market_value": 254200.0, "beds": 3.0, "bath": 2.0, "sqft": 1530.0, "year_built": "1930", "acres": 0.21}, {"parcel_id": "167497", "address": "400 GLENROSE AVE", "lat": "36.126095", "lon": "-86.751724", "sale_price": -1.0, "sale_date": "", "market_value": 371000.0, "beds": 3.0, "bath": 1.0, "sqft": 1435.0, "year_built": "1928", "acres": 0.17}, {"parcel_id": "167778", "address": "330 VIVELLE AVE", "lat": "36.12656", "lon": "-86.751888", "sale_price": -1.0, "sale_date": "", "market_value": 254300.0, "beds": 3.0, "bath": 1.0, "sqft": 792.0, "year_built": "1970", "acres": 0.17}, {"parcel_id": "167779", "address": "0 GLENROSE AVE", "lat": "36.1261", "lon": "-86.751909", "sale_price": null, "sale_date": "", "market_value": null, "beds": null, "bath": 0.0, "sqft": null, "year_built": "", "acres": null}, {"parcel_id": "167780", "address": "404 GLENROSE AVE", "lat": "36.126109", "lon": "-86.752079", "sale_price": -1.0, "sale_date": "", "market_value": 444600.0, "beds": 3.0, "bath": 1.0, "sqft": 1532.0, "year_built": "1940", "acres": 0.17}, {"parcel_id": "168381", "address": "1976 LONEY DR", "lat": "36.129596", "lon": "-86.732424", "sale_price": -1.0, "sale_date": "", "market_value": 357600.0, "beds": 4.0, "bath": 1.5, "sqft": 918.0, "year_built": "1950", "acres": 0.36}, {"parcel_id": "168389", "address": "1983 LAVERGNE CT", "lat": "36.129197", "lon": "-86.731884", "sale_price": -1.0, "sale_date": "", "market_value": 320000.0, "beds": 2.0, "bath": 1.0, "sqft": 1134.0, "year_built": "1950", "acres": 0.36}, {"parcel_id": "168500", "address": "93 SCOBEY DR", "lat": "36.128169", "lon": "-86.735497", "sale_price": -1.0, "sale_date": "", "market_value": 284600.0, "beds": 2.0, "bath": 1.0, "sqft": 1056.0, "year_built": "1950", "acres": 0.3}, {"parcel_id": "168951", "address": "1040 HAROLD DR", "lat": "36.134154", "lon": "-86.709137", "sale_price": null, "sale_date": "", "market_value": null, "beds": null, "bath": 0.0, "sqft": null, "year_built": "", "acres": null}, {"parcel_id": "168953", "address": "1042 HAROLD DR", "lat": "36.134098", "lon": "-86.709126", "sale_price": null, "sale_date": "", "market_value": null, "beds": null, "bath": 0.0, "sqft": null, "year_built": "", "acres": null}, {"parcel_id": "168955", "address": "1044 HAROLD DR", "lat": "36.134041", "lon": "-86.709118", "sale_price": null, "sale_date": "", "market_value": null, "beds": null, "bath": 0.0, "sqft": null, "year_built": "", "acres": null}, {"parcel_id": "168957", "address": "1046 HAROLD DR", "lat": "36.133984", "lon": "-86.70911", "sale_price": null, "sale_date": "", "market_value": null, "beds": null, "bath": 0.0, "sqft": null, "year_built": "", "acres": null}, {"parcel_id": "168959", "address": "1048 HAROLD DR", "lat": "36.133927", "lon": "-86.709102", "sale_price": null, "sale_date": "", "market_value": null, "beds": null, "bath": 0.0, "sqft": null, "year_built": "", "acres": null}, {"parcel_id": "168961", "address": "1050 HAROLD DR", "lat": "36.133869", "lon": "-86.709093", "sale_price": null, "sale_date": "", "market_value": null, "beds": null, "bath": 0.0, "sqft": null, "year_built": "", "acres": null}, {"parcel_id": "168963", "address": "1052 HAROLD DR", "lat": "36.133812", "lon": "-86.709084", "sale_price": null, "sale_date": "", "market_value": null, "beds": null, "bath": 0.0, "sqft": null, "year_built": "", "acres": null}, {"parcel_id": "168965", "address": "1054 HAROLD DR", "lat": "36.133754", "lon": "-86.709073", "sale_price": null, "sale_date": "", "market_value": null, "beds": null, "bath": 0.0, "sqft": null, "year_built": "", "acres": null}, {"parcel_id": "168966", "address": "1055 HAROLD DR", "lat": "36.133688", "lon": "-86.709705", "sale_price": -1.0, "sale_date": "", "market_value": 146600.0, "beds": 2.0, "bath": 1.5, "sqft": 992.0, "year_built": "1973", "acres": 0.0}, {"parcel_id": "168967", "address": "1057 HAROLD DR", "lat": "36.133647", "lon": "-86.7097", "sale_price": -1.0, "sale_date": "", "market_value": 146600.0, "beds": 2.0, "bath": 1.5, "sqft": 992.0, "year_built": "1973", "acres": 0.0}, {"parcel_id": "168970", "address": "1063 HAROLD DR", "lat": "36.133528", "lon": "-86.70968", "sale_price": -1.0, "sale_date": "", "market_value": 146600.0, "beds": 2.0, "bath": 1.5, "sqft": 992.0, "year_built": "1973", "acres": 0.0}, {"parcel_id": "168973", "address": "1069 HAROLD DR", "lat": "36.133411", "lon": "-86.709661", "sale_price": -1.0, "sale_date": "", "market_value": 146600.0, "beds": 2.0, "bath": 1.5, "sqft": 992.0, "year_built": "1973", "acres": 0.0}, {"parcel_id": "168974", "address": "1071 HAROLD DR", "lat": "36.13337", "lon": "-86.709653", "sale_price": -1.0, "sale_date": "", "market_value": 146600.0, "beds": 2.0, "bath": 1.5, "sqft": 992.0, "year_built": "1973", "acres": 0.0}, {"parcel_id": "168975", "address": "1073 HAROLD DR", "lat": "36.13333", "lon": "-86.709649", "sale_price": -1.0, "sale_date": "", "market_value": 146600.0, "beds": 2.0, "bath": 1.5, "sqft": 992.0, "year_built": "1973", "acres": 0.0}, {"parcel_id": "168976", "address": "1077 HAROLD DR", "lat": "36.133351", "lon": "-86.709651", "sale_price": -1.0, "sale_date": "", "market_value": 138100.0, "beds": 1.0, "bath": 1.0, "sqft": 930.0, "year_built": "1973", "acres": 0.0}, {"parcel_id": "168977", "address": "1079 HAROLD DR", "lat": "36.133429", "lon": "-86.709664", "sale_price": -1.0, "sale_date": "", "market_value": 138100.0, "beds": 1.0, "bath": 1.0, "sqft": 930.0, "year_built": "1973", "acres": 0.0}, {"parcel_id": "168979", "address": "1083 HAROLD DR", "lat": "36.133587", "lon": "-86.709691", "sale_price": -1.0, "sale_date": "", "market_value": 138100.0, "beds": 1.0, "bath": 1.0, "sqft": 930.0, "year_built": "1973", "acres": 0.0}, {"parcel_id": "169002", "address": "907 KIRBY DR", "lat": "36.129909", "lon": "-86.697179", "sale_price": -1.0, "sale_date": "", "market_value": 275900.0, "beds": 4.0, "bath": 2.0, "sqft": 1221.0, "year_built": "1963", "acres": 0.39}, {"parcel_id": "169006", "address": "900 KIRBY DR", "lat": "36.130372", "lon": "-86.696116", "sale_price": -1.0, "sale_date": "", "market_value": 284300.0, "beds": 3.0, "bath": 1.0, "sqft": 925.0, "year_built": "1980", "acres": 0.33}, {"parcel_id": "169074", "address": "1058 HAROLD DR", "lat": "36.133973", "lon": "-86.708572", "sale_price": -1.0, "sale_date": "", "market_value": 206800.0, "beds": 3.0, "bath": 1.0, "sqft": 1008.0, "year_built": "1962", "acres": 0.0}, {"parcel_id": "169114", "address": "987 BRILEY PKWY", "lat": "36.129414", "lon": "-86.695757", "sale_price": -1.0, "sale_date": "", "market_value": 251000.0, "beds": 2.0, "bath": 1.0, "sqft": 874.0, "year_built": "1965", "acres": 0.33}, {"parcel_id": "169232", "address": "904 ALADDIN DR", "lat": "36.129328", "lon": "-86.699107", "sale_price": -1.0, "sale_date": "", "market_value": 254700.0, "beds": 2.0, "bath": 1.0, "sqft": 759.0, "year_built": "1980", "acres": 0.32}, {"parcel_id": "169328", "address": "1101 HAROLD DR", "lat": "36.132311", "lon": "-86.709258", "sale_price": 97000.0, "sale_date": "18 Dec 2009", "market_value": 413000.0, "beds": 2.0, "bath": 1.0, "sqft": 1075.0, "year_built": "1958", "acres": 2.35}, {"parcel_id": "169341", "address": "1109 MASSMAN DR", "lat": "36.134858", "lon": "-86.705152", "sale_price": -1.0, "sale_date": "", "market_value": 273300.0, "beds": 2.0, "bath": 1.0, "sqft": 1100.0, "year_built": "1958", "acres": 0.3}, {"parcel_id": "169467", "address": "908 REXDALE DR", "lat": "36.133277", "lon": "-86.704332", "sale_price": -1.0, "sale_date": "", "market_value": 352800.0, "beds": 3.0, "bath": 1.0, "sqft": 1025.0, "year_built": "1965", "acres": 0.4}, {"parcel_id": "169498", "address": "1002 KIRBY DR", "lat": "36.127769", "lon": "-86.696741", "sale_price": -1.0, "sale_date": "", "market_value": 255300.0, "beds": 2.0, "bath": 1.0, "sqft": 1008.0, "year_built": "1980", "acres": 0.22}, {"parcel_id": "169606", "address": "918 COARSEY DR", "lat": "36.126687", "lon": "-86.705287", "sale_price": -1.0, "sale_date": "", "market_value": 179800.0, "beds": 1.0, "bath": 1.0, "sqft": 777.0, "year_built": "1980", "acres": 0.0}, {"parcel_id": "169651", "address": "976 MURFREESBORO PIKE STE A", "lat": "36.130061", "lon": "-86.714828", "sale_price": -1.0, "sale_date": "", "market_value": 206100.0, "beds": 0.0, "bath": 0.0, "sqft": 1140.0, "year_built": "2005", "acres": 0.13}, {"parcel_id": "169652", "address": "976 MURFREESBORO PIKE STE B", "lat": "36.130038", "lon": "-86.714589", "sale_price": -1.0, "sale_date": "", "market_value": 634500.0, "beds": 0.0, "bath": 0.0, "sqft": 4606.0, "year_built": "1972", "acres": 0.32}, {"parcel_id": "169826", "address": "1914 DABBS AVE", "lat": "36.14232", "lon": "-86.706488", "sale_price": -1.0, "sale_date": "", "market_value": 198700.0, "beds": 3.0, "bath": 1.0, "sqft": 950.0, "year_built": "1963", "acres": 0.2}, {"parcel_id": "170110", "address": "1117 THOMPSON PL", "lat": "36.127528", "lon": "-86.705292", "sale_price": -1.0, "sale_date": "", "market_value": 545700.0, "beds": 2.0, "bath": 1.0, "sqft": 2137.0, "year_built": "1970", "acres": 0.71}, {"parcel_id": "170211", "address": "1217 COARSEY DR", "lat": "36.129124", "lon": "-86.702831", "sale_price": -1.0, "sale_date": "", "market_value": 273300.0, "beds": 2.0, "bath": 1.0, "sqft": 912.0, "year_built": "1980", "acres": 0.37}, {"parcel_id": "170294", "address": "1906 LAURINDA DR", "lat": "36.141553", "lon": "-86.705502", "sale_price": -1.0, "sale_date": "", "market_value": 236400.0, "beds": 3.0, "bath": 1.0, "sqft": 950.0, "year_built": "1960", "acres": 0.19}, {"parcel_id": "170296", "address": "1902 LAURINDA DR", "lat": "36.141447", "lon": "-86.705927", "sale_price": -1.0, "sale_date": "", "market_value": 222400.0, "beds": 3.0, "bath": 1.0, "sqft": 950.0, "year_built": "1956", "acres": 0.22}, {"parcel_id": "170306", "address": "1913 LAURINDA DR", "lat": "36.14121", "lon": "-86.704494", "sale_price": -1.0, "sale_date": "", "market_value": 227900.0, "beds": 3.0, "bath": 1.0, "sqft": 950.0, "year_built": "1962", "acres": 0.21}, {"parcel_id": "170357", "address": "1001 GOODBAR DR", "lat": "36.127087", "lon": "-86.701003", "sale_price": -1.0, "sale_date": "", "market_value": 295200.0, "beds": 3.0, "bath": 2.0, "sqft": 1123.0, "year_built": "1975", "acres": 0.34}, {"parcel_id": "170425", "address": "1935 LAURINDA DR", "lat": "36.139897", "lon": "-86.702182", "sale_price": -1.0, "sale_date": "", "market_value": 220900.0, "beds": 3.0, "bath": 1.0, "sqft": 900.0, "year_built": "1964", "acres": 0.22}, {"parcel_id": "170430", "address": "1922 KAREN DR", "lat": "36.140019", "lon": "-86.70337", "sale_price": -1.0, "sale_date": "", "market_value": 232600.0, "beds": 3.0, "bath": 1.0, "sqft": 950.0, "year_built": "1961", "acres": 0.23}, {"parcel_id": "170451", "address": "1904 MARCELLA DR", "lat": "36.13744", "lon": "-86.705395", "sale_price": -1.0, "sale_date": "", "market_value": 218000.0, "beds": 3.0, "bath": 1.0, "sqft": 1000.0, "year_built": "1960", "acres": 0.22}, {"parcel_id": "170452", "address": "1902 MARCELLA DR", "lat": "36.13741", "lon": "-86.705753", "sale_price": -1.0, "sale_date": "", "market_value": 220200.0, "beds": 3.0, "bath": 1.0, "sqft": 1000.0, "year_built": "1960", "acres": 0.22}, {"parcel_id": "170801", "address": "612 CLARIDGE DR", "lat": "36.142947", "lon": "-86.671755", "sale_price": -1.0, "sale_date": "", "market_value": 238700.0, "beds": 2.0, "bath": 1.0, "sqft": 1025.0, "year_built": "1964", "acres": 0.36}, {"parcel_id": "170802", "address": "608 CLARIDGE DR", "lat": "36.142945", "lon": "-86.671382", "sale_price": -1.0, "sale_date": "", "market_value": 234000.0, "beds": 2.0, "bath": 1.0, "sqft": 1050.0, "year_built": "1960", "acres": 0.46}, {"parcel_id": "189759", "address": "2240 GRANDVIEW AVE", "lat": "36.123278", "lon": "-86.752367", "sale_price": -1.0, "sale_date": "", "market_value": 364300.0, "beds": 2.0, "bath": 1.0, "sqft": 764.0, "year_built": "1938", "acres": 0.17}, {"parcel_id": "192075", "address": "358 HESTER AVE", "lat": "36.124973", "lon": "-86.749886", "sale_price": 45000.0, "sale_date": "29 Apr 2014", "market_value": 221500.0, "beds": 2.0, "bath": 1.0, "sqft": 644.0, "year_built": "1928", "acres": 0.21}, {"parcel_id": "192309", "address": "339 E THOMPSON LN", "lat": "36.121407", "lon": "-86.718357", "sale_price": -1.0, "sale_date": "", "market_value": 551900.0, "beds": 4.0, "bath": 2.5, "sqft": 2047.0, "year_built": "1965", "acres": 0.78}, {"parcel_id": "192654", "address": "325 LAWNDALE DR", "lat": "36.123112", "lon": "-86.714803", "sale_price": -1.0, "sale_date": "", "market_value": 386600.0, "beds": 7.0, "bath": 2.0, "sqft": 1863.9725, "year_built": "1955", "acres": 0.72}, {"parcel_id": "192677", "address": "305 BOWWOOD DR", "lat": "36.124402", "lon": "-86.711358", "sale_price": -1.0, "sale_date": "", "market_value": 319900.0, "beds": 3.0, "bath": 1.0, "sqft": 1312.0, "year_built": "1955", "acres": 0.66}, {"parcel_id": "192883", "address": "67 JONELL DR", "lat": "36.121549", "lon": "-86.736351", "sale_price": -1.0, "sale_date": "", "market_value": 262200.0, "beds": 2.0, "bath": 1.0, "sqft": 912.0, "year_built": "1951", "acres": 0.29}, {"parcel_id": "193093", "address": "2238 FOSTER AVE", "lat": "36.122607", "lon": "-86.742401", "sale_price": -1.0, "sale_date": "", "market_value": 263700.0, "beds": 2.0, "bath": 1.0, "sqft": 1166.0, "year_built": "1946", "acres": 0.17}, {"parcel_id": "193355", "address": "130 STIRTON RD", "lat": "36.122884", "lon": "-86.731226", "sale_price": -1.0, "sale_date": "", "market_value": 286800.0, "beds": 2.0, "bath": 1.0, "sqft": 950.0, "year_built": "1956", "acres": 0.3}, {"parcel_id": "193433", "address": "77 LUTIE ST", "lat": "36.116653", "lon": "-86.739484", "sale_price": -1.0, "sale_date": "", "market_value": 254600.0, "beds": 2.0, "bath": 1.0, "sqft": 837.0, "year_built": "1949", "acres": 0.22}, {"parcel_id": "193703", "address": "2314 FOSTER AVE", "lat": "36.120899", "lon": "-86.742613", "sale_price": -1.0, "sale_date": "", "market_value": 267900.0, "beds": 2.0, "bath": 1.0, "sqft": 934.0, "year_built": "1946", "acres": 0.17}, {"parcel_id": "193838", "address": "206 DESOTO DR", "lat": "36.124972", "lon": "-86.732096", "sale_price": null, "sale_date": "", "market_value": null, "beds": null, "bath": 0.0, "sqft": null, "year_built": "", "acres": null}, {"parcel_id": "194465", "address": "2937 LOUISE DR", "lat": "36.107868", "lon": "-86.747919", "sale_price": -1.0, "sale_date": "", "market_value": 214100.0, "beds": 2.0, "bath": 1.0, "sqft": 750.0, "year_built": "1970", "acres": 0.31}, {"parcel_id": "194838", "address": "2605 LIVE OAK RD", "lat": "36.112828", "lon": "-86.727386", "sale_price": -1.0, "sale_date": "", "market_value": 259100.0, "beds": 2.0, "bath": 1.0, "sqft": 1279.0, "year_built": "1952", "acres": 0.42}, {"parcel_id": "195233", "address": "70 E THOMPSON LN", "lat": "36.110369", "lon": "-86.729344", "sale_price": -1.0, "sale_date": "", "market_value": 304000.0, "beds": 2.0, "bath": 1.0, "sqft": 1200.0, "year_built": "1950", "acres": 0.31}, {"parcel_id": "195289", "address": "408 BARRETT RD", "lat": "36.120638", "lon": "-86.720842", "sale_price": -1.0, "sale_date": "", "market_value": 377900.0, "beds": 3.0, "bath": 1.0, "sqft": 1890.0, "year_built": "1955", "acres": 0.48}, {"parcel_id": "195294", "address": "408 WIMPOLE DR", "lat": "36.119223", "lon": "-86.720056", "sale_price": -1.0, "sale_date": "", "market_value": 296600.0, "beds": 4.0, "bath": 2.0, "sqft": 1334.0, "year_built": "1960", "acres": 0.46}, {"parcel_id": "195295", "address": "410 WIMPOLE DR", "lat": "36.119259", "lon": "-86.719741", "sale_price": -1.0, "sale_date": "", "market_value": 298000.0, "beds": 4.0, "bath": 2.0, "sqft": 1334.0, "year_built": "1963", "acres": 0.43}, {"parcel_id": "195353", "address": "2700 GLENMONT CT", "lat": "36.113105", "lon": "-86.722901", "sale_price": -1.0, "sale_date": "", "market_value": 253000.0, "beds": 2.0, "bath": 1.0, "sqft": 925.0, "year_built": "1956", "acres": 0.64}, {"parcel_id": "195404", "address": "420 E THOMPSON LN", "lat": "36.119745", "lon": "-86.717613", "sale_price": -1.0, "sale_date": "", "market_value": 408000.0, "beds": 3.0, "bath": 1.0, "sqft": 1690.0, "year_built": "1980", "acres": 0.73}, {"parcel_id": "195408", "address": "698 CURREY RD", "lat": "36.119095", "lon": "-86.71801", "sale_price": -1.0, "sale_date": "", "market_value": 338000.0, "beds": 3.0, "bath": 1.0, "sqft": 1248.0, "year_built": "1948", "acres": 0.96}, {"parcel_id": "195717", "address": "720 DRUMMOND DR", "lat": "36.113545", "lon": "-86.716335", "sale_price": -1.0, "sale_date": "", "market_value": 289300.0, "beds": 3.0, "bath": 1.0, "sqft": 1478.0, "year_built": "1950", "acres": 0.45}, {"parcel_id": "195786", "address": "708 GREYMONT DR", "lat": "36.119502", "lon": "-86.715062", "sale_price": -1.0, "sale_date": "", "market_value": 278600.0, "beds": 2.0, "bath": 1.0, "sqft": 1133.0, "year_built": "1955", "acres": 0.52}, {"parcel_id": "196085", "address": "743 DRUMMOND CT", "lat": "36.110286", "lon": "-86.713504", "sale_price": -1.0, "sale_date": "", "market_value": 280900.0, "beds": 2.0, "bath": 1.5, "sqft": 1236.0, "year_built": "1952", "acres": 0.89}, {"parcel_id": "196182", "address": "2821 DRUID DR", "lat": "36.110817", "lon": "-86.733539", "sale_price": -1.0, "sale_date": "", "market_value": 244400.0, "beds": 2.0, "bath": 1.0, "sqft": 767.0, "year_built": "1950", "acres": 0.35}, {"parcel_id": "196234", "address": "1303 VENUS DR", "lat": "36.123221", "lon": "-86.699687", "sale_price": -1.0, "sale_date": "", "market_value": 225900.0, "beds": 2.0, "bath": 1.0, "sqft": 790.0, "year_built": "1970", "acres": 0.21}, {"parcel_id": "196240", "address": "1313 VENUS DR", "lat": "36.123131", "lon": "-86.698684", "sale_price": -1.0, "sale_date": "", "market_value": 232400.0, "beds": 2.0, "bath": 1.0, "sqft": 775.0, "year_built": "1970", "acres": 0.23}, {"parcel_id": "196491", "address": "1307 MERCURY DR", "lat": "36.121058", "lon": "-86.700406", "sale_price": -1.0, "sale_date": "", "market_value": 230800.0, "beds": 3.0, "bath": 1.0, "sqft": 1023.0, "year_built": "1960", "acres": 0.28}, {"parcel_id": "196741", "address": "1245 SATURN DR", "lat": "36.120684", "lon": "-86.701884", "sale_price": -1.0, "sale_date": "", "market_value": 345800.0, "beds": 2.0, "bath": 1.0, "sqft": 843.0, "year_built": "1980", "acres": 0.35}, {"parcel_id": "196802", "address": "1263 SCHOOL LN", "lat": "36.110674", "lon": "-86.69799", "sale_price": -1.0, "sale_date": "", "market_value": 399400.0, "beds": 3.0, "bath": 1.5, "sqft": 1302.0, "year_built": "1970", "acres": 0.5}, {"parcel_id": "196885", "address": "414 SOUTHWOOD DR", "lat": "36.11708", "lon": "-86.709329", "sale_price": -1.0, "sale_date": "", "market_value": 191600.0, "beds": 4.0, "bath": 4.0, "sqft": 3350.0, "year_built": "1972", "acres": 1.17}, {"parcel_id": "196886", "address": "0 SOUTHWOOD DR", "lat": "36.117314", "lon": "-86.709135", "sale_price": null, "sale_date": "", "market_value": null, "beds": null, "bath": 0.0, "sqft": null, "year_built": "", "acres": null}, {"parcel_id": "197088", "address": "307 BOWWOOD DR", "lat": "36.124248", "lon": "-86.71106", "sale_price": -1.0, "sale_date": "", "market_value": 365200.0, "beds": 3.0, "bath": 2.0, "sqft": 1368.0, "year_built": "1955", "acres": 0.6}, {"parcel_id": "197092", "address": "318 BOWWOOD DR", "lat": "36.122469", "lon": "-86.710696", "sale_price": -1.0, "sale_date": "", "market_value": 320800.0, "beds": 4.0, "bath": 2.0, "sqft": 2391.0, "year_built": "1955", "acres": 0.76}, {"parcel_id": "197093", "address": "316 BOWWOOD DR", "lat": "36.122646", "lon": "-86.710436", "sale_price": -1.0, "sale_date": "", "market_value": 410600.0, "beds": 3.0, "bath": 2.0, "sqft": 1814.0, "year_built": "1955", "acres": 0.75}, {"parcel_id": "197102", "address": "806 WINTHORNE CT", "lat": "36.121759", "lon": "-86.70958", "sale_price": -1.0, "sale_date": "", "market_value": 386200.0, "beds": 3.0, "bath": 1.5, "sqft": 1769.0, "year_built": "1965", "acres": 0.34}, {"parcel_id": "197103", "address": "804 WINTHORNE CT", "lat": "36.121925", "lon": "-86.709898", "sale_price": -1.0, "sale_date": "", "market_value": 399400.0, "beds": 3.0, "bath": 1.5, "sqft": 1764.0, "year_built": "1965", "acres": 0.48}, {"parcel_id": "197199", "address": "110 NEESE DR", "lat": "36.107644", "lon": "-86.721446", "sale_price": -1.0, "sale_date": "", "market_value": 401100.0, "beds": 4.0, "bath": 1.0, "sqft": 1380.0, "year_built": "1955", "acres": 0.64}, {"parcel_id": "197210", "address": "1139 VULTEE BLVD", "lat": "36.124546", "lon": "-86.709432", "sale_price": null, "sale_date": "", "market_value": null, "beds": null, "bath": 0.0, "sqft": null, "year_built": "", "acres": null}, {"parcel_id": "197212", "address": "312 BOWWOOD DR", "lat": "36.123951", "lon": "-86.709723", "sale_price": -1.0, "sale_date": "", "market_value": 403600.0, "beds": 2.0, "bath": 1.5, "sqft": 1416.0, "year_built": "1956", "acres": 0.96}, {"parcel_id": "197333", "address": "1223 CATINA DR", "lat": "36.12607", "lon": "-86.701481", "sale_price": -1.0, "sale_date": "", "market_value": 186300.0, "beds": 2.0, "bath": 1.0, "sqft": 744.0, "year_built": "1952", "acres": 0.33}, {"parcel_id": "197338", "address": "1222 KERMIT DR", "lat": "36.125372", "lon": "-86.701875", "sale_price": 60000.0, "sale_date": "20 Nov 2009", "market_value": 199900.0, "beds": 2.0, "bath": 1.0, "sqft": 816.0, "year_built": "1952", "acres": 0.3}, {"parcel_id": "197339", "address": "1220 KERMIT DR", "lat": "36.125311", "lon": "-86.702072", "sale_price": -1.0, "sale_date": "", "market_value": 207300.0, "beds": 2.0, "bath": 1.0, "sqft": 816.0, "year_built": "1952", "acres": 0.29}, {"parcel_id": "197356", "address": "1207 KERMIT DR", "lat": "36.124544", "lon": "-86.702737", "sale_price": -1.0, "sale_date": "", "market_value": 203400.0, "beds": 2.0, "bath": 1.0, "sqft": 736.0, "year_built": "1952", "acres": 0.27}, {"parcel_id": "197359", "address": "1201 KERMIT DR", "lat": "36.12436", "lon": "-86.703411", "sale_price": -1.0, "sale_date": "", "market_value": 195600.0, "beds": 2.0, "bath": 1.0, "sqft": 1116.0, "year_built": "1952", "acres": 0.28}, {"parcel_id": "197361", "address": "1202 VULTEE BLVD", "lat": "36.124052", "lon": "-86.703132", "sale_price": -1.0, "sale_date": "", "market_value": 257900.0, "beds": 2.0, "bath": 1.0, "sqft": 1375.0, "year_built": "1952", "acres": 0.34}, {"parcel_id": "197486", "address": "1303 MERCURY DR", "lat": "36.121142", "lon": "-86.700876", "sale_price": -1.0, "sale_date": "", "market_value": 253700.0, "beds": 2.0, "bath": 1.0, "sqft": 850.0, "year_built": "1980", "acres": 0.32}, {"parcel_id": "197600", "address": "1141 VULTEE BLVD", "lat": "36.124252", "lon": "-86.709148", "sale_price": null, "sale_date": "", "market_value": null, "beds": null, "bath": 0.0, "sqft": null, "year_built": "", "acres": null}, {"parcel_id": "197703", "address": "1002 DRUMMOND DR", "lat": "36.105449", "lon": "-86.711288", "sale_price": -1.0, "sale_date": "", "market_value": 399600.0, "beds": 4.0, "bath": 2.0, "sqft": 1625.0, "year_built": "1962", "acres": 1.14}, {"parcel_id": "197739", "address": "1015 GOODBAR DR", "lat": "36.12574", "lon": "-86.700692", "sale_price": -1.0, "sale_date": "", "market_value": 342200.0, "beds": 4.0, "bath": 2.0, "sqft": 1218.0, "year_built": "1970", "acres": 0.61}, {"parcel_id": "197766", "address": "523 GLENPARK DR", "lat": "36.113159", "lon": "-86.707187", "sale_price": -1.0, "sale_date": "", "market_value": 322600.0, "beds": 3.0, "bath": 1.5, "sqft": 1125.0, "year_built": "1963", "acres": 0.39}, {"parcel_id": "197855", "address": "1024 KIRBY DR", "lat": "36.125652", "lon": "-86.697074", "sale_price": -1.0, "sale_date": "", "market_value": 276300.0, "beds": 2.0, "bath": 1.0, "sqft": 1147.0, "year_built": "1965", "acres": 0.23}, {"parcel_id": "197859", "address": "1019 BRILEY PKWY", "lat": "36.126191", "lon": "-86.696502", "sale_price": -1.0, "sale_date": "", "market_value": 251500.0, "beds": 2.0, "bath": 1.0, "sqft": 759.0, "year_built": "1980", "acres": 0.24}, {"parcel_id": "197887", "address": "502 GLENPARK DR", "lat": "36.114428", "lon": "-86.704754", "sale_price": -1.0, "sale_date": "", "market_value": 324000.0, "beds": 3.0, "bath": 1.5, "sqft": 1450.0, "year_built": "1963", "acres": 0.3}, {"parcel_id": "197888", "address": "504 GLENPARK DR", "lat": "36.114262", "lon": "-86.704976", "sale_price": -1.0, "sale_date": "", "market_value": 362300.0, "beds": 4.0, "bath": 1.5, "sqft": 1846.0, "year_built": "1962", "acres": 0.28}, {"parcel_id": "197890", "address": "508 GLENPARK DR", "lat": "36.113908", "lon": "-86.705416", "sale_price": -1.0, "sale_date": "", "market_value": 434700.0, "beds": 3.0, "bath": 2.0, "sqft": 1921.0, "year_built": "1963", "acres": 0.34}, {"parcel_id": "197965", "address": "1317 KERMIT DR", "lat": "36.125288", "lon": "-86.69831", "sale_price": -1.0, "sale_date": "", "market_value": 216900.0, "beds": 2.0, "bath": 1.0, "sqft": 750.0, "year_built": "1960", "acres": 0.26}, {"parcel_id": "198107", "address": "1328 VENUS DR", "lat": "36.123582", "lon": "-86.696961", "sale_price": -1.0, "sale_date": "", "market_value": 296900.0, "beds": 2.0, "bath": 1.0, "sqft": 936.0, "year_built": "1980", "acres": 0.23}, {"parcel_id": "198111", "address": "1320 VENUS DR", "lat": "36.123658", "lon": "-86.697773", "sale_price": -1.0, "sale_date": "", "market_value": 256800.0, "beds": 2.0, "bath": 1.0, "sqft": 768.0, "year_built": "1980", "acres": 0.23}, {"parcel_id": "198139", "address": "3423 MCGAVOCK PIKE", "lat": "36.110788", "lon": "-86.702634", "sale_price": -1.0, "sale_date": "", "market_value": 663400.0, "beds": 3.0, "bath": 3.5, "sqft": 1690.0, "year_built": "2005", "acres": 1.43}, {"parcel_id": "199068", "address": "500 CATALINA DR", "lat": "36.104853", "lon": "-86.702534", "sale_price": -1.0, "sale_date": "", "market_value": 427700.0, "beds": 3.0, "bath": 1.5, "sqft": 1895.0, "year_built": "1961", "acres": 0.64}, {"parcel_id": "199210", "address": "1110 TARA ANN CT", "lat": "36.106759", "lon": "-86.704602", "sale_price": 52125.0, "sale_date": "18 Dec 2013", "market_value": 206400.0, "beds": 2.0, "bath": 1.5, "sqft": 1020.0, "year_built": "1984", "acres": 0.12}, {"parcel_id": "199317", "address": "1108 TARA ANN CT", "lat": "36.106713", "lon": "-86.704519", "sale_price": 52125.0, "sale_date": "18 Dec 2013", "market_value": 206400.0, "beds": 2.0, "bath": 1.5, "sqft": 1020.0, "year_built": "1984", "acres": 0.14}, {"parcel_id": "199331", "address": "411 FORRESTER DR", "lat": "36.10548", "lon": "-86.696239", "sale_price": -1.0, "sale_date": "", "market_value": 176000.0, "beds": 3.0, "bath": 1.0, "sqft": 1132.0, "year_built": "1950", "acres": 0.45}, {"parcel_id": "199428", "address": "327 FORRESTER DR", "lat": "36.107298", "lon": "-86.695198", "sale_price": -1.0, "sale_date": "", "market_value": 184900.0, "beds": 2.0, "bath": 1.0, "sqft": 884.0, "year_built": "1950", "acres": 0.34}, {"parcel_id": "199650", "address": "4001 ANDERSON RD UNIT G61", "lat": "36.104808", "lon": "-86.600385", "sale_price": -1.0, "sale_date": "", "market_value": 227700.0, "beds": 2.0, "bath": 1.5, "sqft": 1353.0, "year_built": "1978", "acres": 0.0}, {"parcel_id": "199675", "address": "1325 CONVAIR CIR", "lat": "36.107075", "lon": "-86.691599", "sale_price": -1.0, "sale_date": "", "market_value": 267300.0, "beds": 3.0, "bath": 1.5, "sqft": 1198.0, "year_built": "1985", "acres": 0.27}, {"parcel_id": "199693", "address": "1306 PORTVIEW DR", "lat": "36.10677", "lon": "-86.693782", "sale_price": -1.0, "sale_date": "", "market_value": 152900.0, "beds": 2.0, "bath": 1.0, "sqft": 792.0, "year_built": "1950", "acres": 0.35}, {"parcel_id": "199702", "address": "1307 PORTVIEW DR", "lat": "36.106113", "lon": "-86.694126", "sale_price": -1.0, "sale_date": "", "market_value": 206100.0, "beds": 2.0, "bath": 1.0, "sqft": 1056.0, "year_built": "1951", "acres": 0.25}, {"parcel_id": "199704", "address": "1311 PORTVIEW DR", "lat": "36.10609", "lon": "-86.693655", "sale_price": -1.0, "sale_date": "", "market_value": 154600.0, "beds": 2.0, "bath": 1.0, "sqft": 816.0, "year_built": "1951", "acres": 0.26}, {"parcel_id": "199800", "address": "1329 PORTVIEW DR", "lat": "36.105996", "lon": "-86.691529", "sale_price": -1.0, "sale_date": "", "market_value": 209700.0, "beds": 2.0, "bath": 1.0, "sqft": 884.0, "year_built": "1950", "acres": 0.26}, {"parcel_id": "200095", "address": "1714 REYNOLDS RD", "lat": "36.106851", "lon": "-86.647496", "sale_price": -1.0, "sale_date": "", "market_value": 286000.0, "beds": 2.0, "bath": 1.5, "sqft": 1150.0, "year_built": "1977", "acres": 1.0}, {"parcel_id": "213588", "address": "517 PATTERSON ST", "lat": "36.102847", "lon": "-86.746419", "sale_price": -1.0, "sale_date": "", "market_value": 381900.0, "beds": 2.0, "bath": 2.0, "sqft": 1260.0, "year_built": "1953", "acres": 0.23}, {"parcel_id": "216295", "address": "3332 GOODLAND RD", "lat": "36.097023", "lon": "-86.723948", "sale_price": -1.0, "sale_date": "", "market_value": 430400.0, "beds": 3.0, "bath": 2.0, "sqft": 1350.0, "year_built": "1955", "acres": 0.39}, {"parcel_id": "217241", "address": "3313 DUMAS DR", "lat": "36.099021", "lon": "-86.724774", "sale_price": -1.0, "sale_date": "", "market_value": 358400.0, "beds": 2.0, "bath": 1.0, "sqft": 1040.0, "year_built": "1959", "acres": 0.37}, {"parcel_id": "217531", "address": "618 OLD EZELL RD", "lat": "36.097457", "lon": "-86.674076", "sale_price": -1.0, "sale_date": "", "market_value": 274900.0, "beds": 3.0, "bath": 1.0, "sqft": 966.0, "year_built": "1960", "acres": 2.0}, {"parcel_id": "218513", "address": "329 TAMPA DR", "lat": "36.087542", "lon": "-86.715276", "sale_price": -1.0, "sale_date": "", "market_value": 254500.0, "beds": 3.0, "bath": 1.0, "sqft": 988.0, "year_built": "1962", "acres": 0.28}, {"parcel_id": "218540", "address": "500 PARAGON MILLS RD APT D2", "lat": "36.088376", "lon": "-86.725779", "sale_price": -1.0, "sale_date": "", "market_value": 185400.0, "beds": 2.0, "bath": 1.5, "sqft": 986.0, "year_built": "1969", "acres": 0.0}, {"parcel_id": "219530", "address": "2027 RICE AVE", "lat": "36.095089", "lon": "-86.655528", "sale_price": -1.0, "sale_date": "", "market_value": 211000.0, "beds": 2.0, "bath": 1.0, "sqft": 768.0, "year_built": "1957", "acres": 0.43}, {"parcel_id": "219539", "address": "301 FRANKLIN LIMESTONE RD", "lat": "36.093536", "lon": "-86.661522", "sale_price": -1.0, "sale_date": "", "market_value": 643700.0, "beds": 2.0, "bath": 1.0, "sqft": 1530.0, "year_built": "1940", "acres": 12.0}, {"parcel_id": "219540", "address": "331 FRANKLIN LIMESTONE RD", "lat": "36.092573", "lon": "-86.662581", "sale_price": -1.0, "sale_date": "", "market_value": 1223400.0, "beds": 1.0, "bath": 1.0, "sqft": 2716.0, "year_built": "1930", "acres": 14.72}, {"parcel_id": "219543", "address": "0 FRANKLIN LIMESTONE RD", "lat": "36.088199", "lon": "-86.664729"}, {"parcel_id": "219664", "address": "322 FRANKLIN LIMESTONE RD", "lat": "36.091828", "lon": "-86.659449", "sale_price": -1.0, "sale_date": "", "market_value": 463300.0, "beds": 3.0, "bath": 2.0, "sqft": 1592.0, "year_built": "1956", "acres": 2.92}, {"parcel_id": "220388", "address": "404 EZELL PIKE", "lat": "36.097643", "lon": "-86.672768", "sale_price": -1.0, "sale_date": "", "market_value": 421000.0, "beds": 3.0, "bath": 1.0, "sqft": 2138.0, "year_built": "1900", "acres": 0.84}, {"parcel_id": "220397", "address": "0 EZELL PIKE", "lat": "36.097172", "lon": "-86.673205", "sale_price": null, "sale_date": "", "market_value": null, "beds": null, "bath": 0.0, "sqft": null, "year_built": "", "acres": null}, {"parcel_id": "220551", "address": "1609 CITATION DR", "lat": "36.100297", "lon": "-86.670478", "sale_price": -1.0, "sale_date": "", "market_value": 311700.0, "beds": 3.0, "bath": 1.5, "sqft": 1650.0, "year_built": "1965", "acres": 0.52}, {"parcel_id": "220917", "address": "439A EZELL PIKE", "lat": "36.09455", "lon": "-86.675514", "sale_price": -1.0, "sale_date": "", "market_value": 364200.0, "beds": 4.0, "bath": 1.5, "sqft": 2066.0, "year_built": "1950", "acres": 0.75}, {"parcel_id": "221345", "address": "2028 RICE AVE", "lat": "36.095302", "lon": "-86.65494", "sale_price": -1.0, "sale_date": "", "market_value": 188600.0, "beds": 3.0, "bath": 1.0, "sqft": 1217.0, "year_built": "1951", "acres": 0.15}, {"parcel_id": "222212", "address": "1914 OLD MURFREESBORO PIKE", "lat": "36.099039", "lon": "-86.656366", "sale_price": -1.0, "sale_date": "", "market_value": 250000.0, "beds": 3.0, "bath": 1.0, "sqft": 1904.0, "year_built": "1950", "acres": 1.5}, {"parcel_id": "222222", "address": "341 FRANKLIN LIMESTONE RD", "lat": "36.091656", "lon": "-86.663826", "sale_price": null, "sale_date": "", "market_value": null, "beds": null, "bath": 0.0, "sqft": null, "year_built": "", "acres": null}, {"parcel_id": "222255", "address": "2007 FORGES DR", "lat": "36.089777", "lon": "-86.664328", "sale_price": 71000.0, "sale_date": "11 Dec 2009", "market_value": 238900.0, "beds": 3.0, "bath": 1.0, "sqft": 925.0, "year_built": "1962", "acres": 0.6}, {"parcel_id": "222480", "address": "0 FRANKLIN LIMESTONE RD", "lat": "36.091266", "lon": "-86.661993", "sale_price": null, "sale_date": "", "market_value": null, "beds": null, "bath": 0.0, "sqft": null, "year_built": "", "acres": null}, {"parcel_id": "222615", "address": "1629 CITATION DR", "lat": "36.102183", "lon": "-86.668893", "sale_price": -1.0, "sale_date": "", "market_value": 312900.0, "beds": 3.0, "bath": 1.5, "sqft": 1875.0, "year_built": "1980", "acres": 0.55}, {"parcel_id": "222722", "address": "1709 D VILLE DR", "lat": "36.099957", "lon": "-86.666894", "sale_price": -1.0, "sale_date": "", "market_value": 249200.0, "beds": 3.0, "bath": 1.0, "sqft": 1302.0, "year_built": "1963", "acres": 0.27}, {"parcel_id": "222728", "address": "1714 SOUTHWIND DR", "lat": "36.099348", "lon": "-86.668216", "sale_price": -1.0, "sale_date": "", "market_value": 237600.0, "beds": 3.0, "bath": 1.0, "sqft": 1237.0, "year_built": "1962", "acres": 0.32}, {"parcel_id": "222849", "address": "1738 SOUTHWIND DR", "lat": "36.099516", "lon": "-86.664562", "sale_price": -1.0, "sale_date": "", "market_value": 254200.0, "beds": 3.0, "bath": 1.0, "sqft": 1100.0, "year_built": "1963", "acres": 0.38}, {"parcel_id": "222956", "address": "318 LADYBIRD DR", "lat": "36.099974", "lon": "-86.663776", "sale_price": -1.0, "sale_date": "", "market_value": 323500.0, "beds": 3.0, "bath": 1.5, "sqft": 1700.0, "year_built": "1963", "acres": 0.48}, {"parcel_id": "223330", "address": "330 LADYBIRD DR", "lat": "36.098429", "lon": "-86.663963", "sale_price": -1.0, "sale_date": "", "market_value": 224800.0, "beds": 3.0, "bath": 1.0, "sqft": 1000.0, "year_built": "1963", "acres": 0.29}, {"parcel_id": "225805", "address": "3515 SENECA FOREST DR", "lat": "36.090919", "lon": "-86.610402", "sale_price": 60000.0, "sale_date": "18 Dec 2013", "market_value": 212000.0, "beds": 3.0, "bath": 1.0, "sqft": 1220.0, "year_built": "1985", "acres": 0.0}, {"parcel_id": "226511", "address": "121 TIMBER RIDGE DR", "lat": "36.096604", "lon": "-86.605701", "sale_price": -1.0, "sale_date": "", "market_value": 346000.0, "beds": 4.0, "bath": 3.0, "sqft": 2097.0, "year_built": "1970", "acres": 0.32}, {"parcel_id": "226814", "address": "722 HOLDER DR", "lat": "36.083456", "lon": "-86.614045", "sale_price": -1.0, "sale_date": "", "market_value": 211500.0, "beds": 2.0, "bath": 1.5, "sqft": 1024.0, "year_built": "1984", "acres": 0.05}, {"parcel_id": "226932", "address": "304 STARBOARD CT", "lat": "36.085086", "lon": "-86.61094", "sale_price": -1.0, "sale_date": "", "market_value": 294700.0, "beds": 3.0, "bath": 3.0, "sqft": 1572.0, "year_built": "1987", "acres": 0.27}, {"parcel_id": "227048", "address": "101 BLUE MIST CT", "lat": "36.091407", "lon": "-86.606529", "sale_price": -1.0, "sale_date": "", "market_value": 338800.0, "beds": 4.0, "bath": 2.5, "sqft": 2120.0, "year_built": "1968", "acres": 0.39}, {"parcel_id": "232586", "address": "210 OLD HICKORY BLVD APT 44", "lat": "36.080028", "lon": "-86.918392", "sale_price": -1.0, "sale_date": "", "market_value": 202300.0, "beds": 1.0, "bath": 1.5, "sqft": 720.0, "year_built": "1969", "acres": 0.0}, {"parcel_id": "232587", "address": "210 OLD HICKORY BLVD APT 45", "lat": "36.080136", "lon": "-86.918349", "sale_price": -1.0, "sale_date": "", "market_value": 205300.0, "beds": 1.0, "bath": 1.0, "sqft": 730.0, "year_built": "1969", "acres": 0.0}, {"parcel_id": "240971", "address": "370 WALLACE RD APT D13", "lat": "36.079085", "lon": "-86.723809", "sale_price": -1.0, "sale_date": "", "market_value": 168400.0, "beds": 2.0, "bath": 1.0, "sqft": 972.0, "year_built": "1970", "acres": 0.0}, {"parcel_id": "241826", "address": "4817 FOLEY DR", "lat": "36.077792", "lon": "-86.716981", "sale_price": -1.0, "sale_date": "", "market_value": 297300.0, "beds": 3.0, "bath": 1.0, "sqft": 1025.0, "year_built": "1958", "acres": 0.73}, {"parcel_id": "241827", "address": "4821 FOLEY DR", "lat": "36.077537", "lon": "-86.717108", "sale_price": 109000.0, "sale_date": "23 Nov 2009", "market_value": 285700.0, "beds": 3.0, "bath": 1.0, "sqft": 1231.0, "year_built": "1958", "acres": 0.64}, {"parcel_id": "241966", "address": "267 WALLACE RD", "lat": "36.078978", "lon": "-86.710765", "sale_price": -1.0, "sale_date": "", "market_value": 381200.0, "beds": 3.0, "bath": 2.0, "sqft": 1475.0, "year_built": "1966", "acres": 0.23}, {"parcel_id": "243208", "address": "583 WHISPERING HILLS DR", "lat": "36.065988", "lon": "-86.730132", "sale_price": -1.0, "sale_date": "", "market_value": 405500.0, "beds": 3.0, "bath": 1.5, "sqft": 1250.0, "year_built": "1964", "acres": 0.68}, {"parcel_id": "243734", "address": "690 BREWER DR", "lat": "36.065363", "lon": "-86.736841", "sale_price": -1.0, "sale_date": "", "market_value": 350900.0, "beds": 3.0, "bath": 1.5, "sqft": 1250.0, "year_built": "1966", "acres": 0.34}, {"parcel_id": "244471", "address": "583 HIGHCREST DR", "lat": "36.06472", "lon": "-86.730799", "sale_price": -1.0, "sale_date": "", "market_value": 390100.0, "beds": 3.0, "bath": 1.0, "sqft": 1025.0, "year_built": "1956", "acres": 0.5}, {"parcel_id": "244844", "address": "3812 TURLEY DR", "lat": "36.071804", "lon": "-86.708512", "sale_price": -1.0, "sale_date": "", "market_value": 357700.0, "beds": 2.0, "bath": 2.0, "sqft": 1743.0, "year_built": "1958", "acres": 0.42}, {"parcel_id": "245218", "address": "4942 HOPEDALE DR", "lat": "36.071084", "lon": "-86.715812", "sale_price": -1.0, "sale_date": "", "market_value": 269100.0, "beds": 3.0, "bath": 1.0, "sqft": 904.0, "year_built": "1955", "acres": 0.49}, {"parcel_id": "245483", "address": "518 SOUTHCREST DR", "lat": "36.062211", "lon": "-86.725684", "sale_price": -1.0, "sale_date": "", "market_value": 325500.0, "beds": 2.0, "bath": 1.0, "sqft": 1372.0, "year_built": "1955", "acres": 0.64}, {"parcel_id": "245567", "address": "243 WILLARD DR", "lat": "36.071569", "lon": "-86.699517", "sale_price": -1.0, "sale_date": "", "market_value": 384200.0, "beds": 4.0, "bath": 2.0, "sqft": 1625.0, "year_built": "1965", "acres": 1.61}, {"parcel_id": "246572", "address": "412 DERRICK CT", "lat": "36.07456", "lon": "-86.69072", "sale_price": -1.0, "sale_date": "", "market_value": 194500.0, "beds": 2.0, "bath": 1.5, "sqft": 1026.0, "year_built": "1985", "acres": 0.14}, {"parcel_id": "246582", "address": "1540 GASSER DR", "lat": "36.07686", "lon": "-86.683104", "sale_price": -1.0, "sale_date": "", "market_value": 293900.0, "beds": 3.0, "bath": 1.5, "sqft": 1075.0, "year_built": "1963", "acres": 0.28}, {"parcel_id": "247055", "address": "2530 EDGE O LAKE DR", "lat": "36.08087", "lon": "-86.642073", "sale_price": -1.0, "sale_date": "", "market_value": 290300.0, "beds": 4.0, "bath": 2.0, "sqft": 1250.0, "year_built": "1966", "acres": 0.26}, {"parcel_id": "247292", "address": "1513 DENISE CT", "lat": "36.074743", "lon": "-86.686411", "sale_price": -1.0, "sale_date": "", "market_value": 246500.0, "beds": 3.0, "bath": 1.0, "sqft": 1025.0, "year_built": "1970", "acres": 0.28}, {"parcel_id": "247311", "address": "124 RADER DR", "lat": "36.074272", "lon": "-86.685216", "sale_price": -1.0, "sale_date": "", "market_value": 285100.0, "beds": 3.0, "bath": 1.5, "sqft": 1000.0, "year_built": "1970", "acres": 0.29}, {"parcel_id": "247544", "address": "124 ELIZABETHS CT", "lat": "36.079654", "lon": "-86.659447", "sale_price": -1.0, "sale_date": "", "market_value": 229900.0, "beds": 2.0, "bath": 1.5, "sqft": 1099.0, "year_built": "1985", "acres": 0.0}, {"parcel_id": "247570", "address": "2478 SCOTT VALLEY DR", "lat": "36.079968", "lon": "-86.644486", "sale_price": -1.0, "sale_date": "", "market_value": 181800.0, "beds": 2.0, "bath": 1.5, "sqft": 1008.0, "year_built": "1985", "acres": 0.16}, {"parcel_id": "248036", "address": "2462 SCOTT VALLEY DR", "lat": "36.080501", "lon": "-86.645034", "sale_price": -1.0, "sale_date": "", "market_value": 183500.0, "beds": 2.0, "bath": 1.5, "sqft": 1008.0, "year_built": "1985", "acres": 0.12}, {"parcel_id": "248048", "address": "2438 SCOTT VALLEY DR", "lat": "36.081309", "lon": "-86.645669", "sale_price": -1.0, "sale_date": "", "market_value": 181800.0, "beds": 2.0, "bath": 1.5, "sqft": 1008.0, "year_built": "1985", "acres": 0.13}, {"parcel_id": "248063", "address": "2408 SCOTT VALLEY DR", "lat": "36.082427", "lon": "-86.646131", "sale_price": -1.0, "sale_date": "", "market_value": 182600.0, "beds": 2.0, "bath": 1.5, "sqft": 1008.0, "year_built": "1985", "acres": 0.14}, {"parcel_id": "248532", "address": "2480 SCOTT VALLEY DR", "lat": "36.079834", "lon": "-86.644405", "sale_price": -1.0, "sale_date": "", "market_value": 181800.0, "beds": 2.0, "bath": 1.5, "sqft": 1008.0, "year_built": "1985", "acres": 0.16}, {"parcel_id": "248541", "address": "2440 SCOTT VALLEY DR", "lat": "36.081236", "lon": "-86.645614", "sale_price": -1.0, "sale_date": "", "market_value": 181800.0, "beds": 2.0, "bath": 1.5, "sqft": 1008.0, "year_built": "1985", "acres": 0.13}, {"parcel_id": "249412", "address": "0 GOODWIN RD", "lat": "36.064917", "lon": "-86.675862", "sale_price": null, "sale_date": "", "market_value": null, "beds": null, "bath": 0.0, "sqft": null, "year_built": "", "acres": null}, {"parcel_id": "249413", "address": "0 GOODWIN RD", "lat": "36.064716", "lon": "-86.675713", "sale_price": null, "sale_date": "", "market_value": null, "beds": null, "bath": 0.0, "sqft": null, "year_built": "", "acres": null}, {"parcel_id": "249621", "address": "721 RICHARDS RD", "lat": "36.067571", "lon": "-86.666981", "sale_price": -1.0, "sale_date": "", "market_value": 267700.0, "beds": 3.0, "bath": 1.0, "sqft": 1350.0, "year_built": "1968", "acres": 0.22}, {"parcel_id": "249730", "address": "201 WHORLEY DR", "lat": "36.081469", "lon": "-86.626226", "sale_price": -1.0, "sale_date": "", "market_value": 327900.0, "beds": 4.0, "bath": 2.0, "sqft": 1940.0, "year_built": "1965", "acres": 0.23}, {"parcel_id": "250286", "address": "242 HAYWOOD LN", "lat": "36.070656", "lon": "-86.699555", "sale_price": -1.0, "sale_date": "", "market_value": 364300.0, "beds": 4.0, "bath": 2.0, "sqft": 1600.0, "year_built": "1965", "acres": 1.37}, {"parcel_id": "250507", "address": "2608 EDGE O LAKE DR", "lat": "36.082448", "lon": "-86.637966", "sale_price": -1.0, "sale_date": "", "market_value": 329300.0, "beds": 3.0, "bath": 2.0, "sqft": 1550.0, "year_built": "1961", "acres": 0.33}, {"parcel_id": "251108", "address": "204 APOLLO CIR", "lat": "36.069761", "lon": "-86.667232", "sale_price": -1.0, "sale_date": "", "market_value": 279700.0, "beds": 3.0, "bath": 1.5, "sqft": 1080.0, "year_built": "1974", "acres": 0.28}, {"parcel_id": "251226", "address": "445 CLEARWATER DR", "lat": "36.079075", "lon": "-86.627127", "sale_price": -1.0, "sale_date": "", "market_value": 257600.0, "beds": 3.0, "bath": 1.5, "sqft": 1155.0, "year_built": "1967", "acres": 0.32}, {"parcel_id": "251235", "address": "805 HAWAIIAN VW", "lat": "36.073831", "lon": "-86.674669", "sale_price": -1.0, "sale_date": "", "market_value": 260000.0, "beds": 3.0, "bath": 1.5, "sqft": 1304.0, "year_built": "1972", "acres": 0.18}, {"parcel_id": "251802", "address": "4901 CROSBY LN", "lat": "36.063414", "lon": "-86.709862", "sale_price": -1.0, "sale_date": "", "market_value": 258300.0, "beds": 3.0, "bath": 1.0, "sqft": 950.0, "year_built": "1957", "acres": 0.34}, {"parcel_id": "252461", "address": "2640 RAVINE DR", "lat": "36.081337", "lon": "-86.632734", "sale_price": -1.0, "sale_date": "", "market_value": 294600.0, "beds": 3.0, "bath": 1.5, "sqft": 1725.0, "year_built": "1968", "acres": 0.3}, {"parcel_id": "252674", "address": "2840 DESPLANE DR", "lat": "36.07743", "lon": "-86.627072", "sale_price": -1.0, "sale_date": "", "market_value": 274600.0, "beds": 3.0, "bath": 1.5, "sqft": 1228.0, "year_built": "1972", "acres": 0.26}, {"parcel_id": "253326", "address": "2591 MURFREESBORO PIKE", "lat": "36.074531", "lon": "-86.639421", "sale_price": -1.0, "sale_date": "", "market_value": 2056500.0, "beds": 0.0, "bath": 0.0, "sqft": 7802.0, "year_built": "1980", "acres": 2.05}, {"parcel_id": "253995", "address": "311 RURAL HILL CT", "lat": "36.076579", "lon": "-86.63828", "sale_price": -1.0, "sale_date": "", "market_value": 403000.0, "beds": 3.0, "bath": 1.5, "sqft": 1700.0, "year_built": "1975", "acres": 1.51}, {"parcel_id": "257549", "address": "2880 CREEKVIEW DR", "lat": "36.074481", "lon": "-86.624528", "sale_price": -1.0, "sale_date": "", "market_value": 272000.0, "beds": 4.0, "bath": 2.0, "sqft": 1675.0, "year_built": "1971", "acres": 0.28}, {"parcel_id": "257578", "address": "3006 WOODYMORE PL", "lat": "36.077277", "lon": "-86.610033", "sale_price": -1.0, "sale_date": "", "market_value": 223200.0, "beds": 3.0, "bath": 2.0, "sqft": 1281.0, "year_built": "1986", "acres": 0.13}, {"parcel_id": "258497", "address": "1117 ELKADER CT S", "lat": "36.07829", "lon": "-86.600772", "sale_price": -1.0, "sale_date": "", "market_value": 398600.0, "beds": 3.0, "bath": 3.0, "sqft": 2192.0, "year_built": "1988", "acres": 0.42}, {"parcel_id": "259876", "address": "820 HOLDER CT", "lat": "36.080674", "lon": "-86.612229", "sale_price": -1.0, "sale_date": "", "market_value": 366600.0, "beds": 4.0, "bath": 4.0, "sqft": 2048.0, "year_built": "1984", "acres": 0.25}, {"parcel_id": "259878", "address": "817 HOLDER CT", "lat": "36.080924", "lon": "-86.61205", "sale_price": -1.0, "sale_date": "", "market_value": 366600.0, "beds": 4.0, "bath": 4.0, "sqft": 2048.0, "year_built": "1984", "acres": 0.36}, {"parcel_id": "260006", "address": "3004 WOODYMORE PL", "lat": "36.077228", "lon": "-86.609843", "sale_price": -1.0, "sale_date": "", "market_value": 223800.0, "beds": 3.0, "bath": 2.0, "sqft": 1286.0, "year_built": "1986", "acres": 0.14}, {"parcel_id": "260092", "address": "3263 LUANN DR", "lat": "36.069517", "lon": "-86.619369", "sale_price": -1.0, "sale_date": "", "market_value": 207000.0, "beds": 2.0, "bath": 1.5, "sqft": 1046.0, "year_built": "1985", "acres": 0.14}, {"parcel_id": "261520", "address": "3265 LUANN DR", "lat": "36.069418", "lon": "-86.619283", "sale_price": -1.0, "sale_date": "", "market_value": 212700.0, "beds": 2.0, "bath": 2.0, "sqft": 1098.0, "year_built": "1985", "acres": 0.15}, {"parcel_id": "261521", "address": "3261 LUANN DR", "lat": "36.069614", "lon": "-86.619446", "sale_price": -1.0, "sale_date": "", "market_value": 205500.0, "beds": 2.0, "bath": 1.5, "sqft": 1046.0, "year_built": "1985", "acres": 0.13}, {"parcel_id": "262085", "address": "5304 FOREST ACRES DR", "lat": "36.055556", "lon": "-86.779665", "sale_price": null, "sale_date": "", "market_value": null, "beds": null, "bath": 0.0, "sqft": null, "year_built": "", "acres": null}, {"parcel_id": "262598", "address": "664 HILL RD", "lat": "36.048602", "lon": "-86.759969", "sale_price": -1.0, "sale_date": "", "market_value": 1098300.0, "beds": 5.0, "bath": 2.5, "sqft": 2622.0, "year_built": "1995", "acres": 0.92}, {"parcel_id": "262601", "address": "100 MAXWELL XING", "lat": "36.049539", "lon": "-86.760656", "sale_price": -1.0, "sale_date": "", "market_value": 1670800.0, "beds": 4.0, "bath": 4.0, "sqft": 6206.0, "year_built": "1994", "acres": 1.71}, {"parcel_id": "270903", "address": "247 BENZING RD", "lat": "36.046953", "lon": "-86.68718", "sale_price": -1.0, "sale_date": "", "market_value": 289600.0, "beds": 2.0, "bath": 1.5, "sqft": 1326.0, "year_built": "1950", "acres": 1.69}, {"parcel_id": "270937", "address": "5117 COLEMONT DR", "lat": "36.055566", "lon": "-86.700411", "sale_price": -1.0, "sale_date": "", "market_value": 300500.0, "beds": 4.0, "bath": 2.0, "sqft": 1662.0, "year_built": "1973", "acres": 0.28}, {"parcel_id": "273978", "address": "217 OLD TUSCULUM RD", "lat": "36.053479", "lon": "-86.69581", "sale_price": -1.0, "sale_date": "", "market_value": 279200.0, "beds": 3.0, "bath": 1.0, "sqft": 1050.0, "year_built": "1972", "acres": 0.22}, {"parcel_id": "276911", "address": "355 OCALA DR", "lat": "36.051952", "lon": "-86.708447", "sale_price": 130000.0, "sale_date": "23 May 2011", "market_value": 396300.0, "beds": 3.0, "bath": 2.5, "sqft": 1400.0, "year_built": "1961", "acres": 0.88}, {"parcel_id": "277342", "address": "510 PARK CT", "lat": "36.058621", "lon": "-86.707637", "sale_price": -1.0, "sale_date": "", "market_value": 278900.0, "beds": 3.0, "bath": 2.0, "sqft": 1024.0, "year_built": "1990", "acres": 0.09}, {"parcel_id": "282125", "address": "12486 OLD HICKORY BLVD", "lat": "36.041495", "lon": "-86.601341", "sale_price": -1.0, "sale_date": "", "market_value": 675100.0, "beds": 2.0, "bath": 1.0, "sqft": 720.0, "year_built": "1947", "acres": 6.68}, {"parcel_id": "282131", "address": "12466 OLD HICKORY BLVD", "lat": "36.041738", "lon": "-86.599452", "sale_price": -1.0, "sale_date": "", "market_value": 201500.0, "beds": 3.0, "bath": 1.0, "sqft": 1055.0, "year_built": "1950", "acres": 2.0}, {"parcel_id": "286459", "address": "508 CEDARMONT DR", "lat": "36.037137", "lon": "-86.705747", "sale_price": -1.0, "sale_date": "", "market_value": 175200.0, "beds": 2.0, "bath": 1.0, "sqft": 750.0, "year_built": "1985", "acres": 0.1}, {"parcel_id": "29661", "address": "1108 ELLISTON ST", "lat": "36.259274", "lon": "-86.649883", "sale_price": -1.0, "sale_date": "", "market_value": 207800.0, "beds": 3.0, "bath": 1.0, "sqft": 851.0, "year_built": "1928", "acres": 0.07}, {"parcel_id": "29856", "address": "406 RAYON DR", "lat": "36.271492", "lon": "-86.663929", "sale_price": -1.0, "sale_date": "", "market_value": 202900.0, "beds": 3.0, "bath": 1.0, "sqft": 1408.0, "year_built": "1930", "acres": 0.17}, {"parcel_id": "33748", "address": "3212B SPEARS RD", "lat": "36.237506", "lon": "-86.779483", "sale_price": -1.0, "sale_date": "", "market_value": 269700.0, "beds": 4.0, "bath": 2.0, "sqft": 1404.0, "year_built": "1964", "acres": 0.19}, {"parcel_id": "35066", "address": "837 E MEADE AVE", "lat": "36.252715", "lon": "-86.714812", "sale_price": null, "sale_date": "", "market_value": null, "beds": null, "bath": 0.0, "sqft": null, "year_built": "", "acres": null}, {"parcel_id": "35067", "address": "837 E MEADE AVE", "lat": "36.252857", "lon": "-86.714705", "sale_price": -1.0, "sale_date": "", "market_value": 296500.0, "beds": 2.0, "bath": 2.0, "sqft": 1752.0, "year_built": "1941", "acres": 0.2}, {"parcel_id": "35335", "address": "213 E WEBSTER ST", "lat": "36.251533", "lon": "-86.715587", "sale_price": -1.0, "sale_date": "", "market_value": 483100.0, "beds": 4.0, "bath": 4.0, "sqft": 2176.0, "year_built": "1981", "acres": 0.35}, {"parcel_id": "41935", "address": "109 22ND ST", "lat": "36.248767", "lon": "-86.641767", "sale_price": -1.0, "sale_date": "", "market_value": 223200.0, "beds": 3.0, "bath": 1.0, "sqft": 894.0, "year_built": "1938", "acres": 0.13}, {"parcel_id": "42461", "address": "1403 BRYAN ST", "lat": "36.256175", "lon": "-86.650695", "sale_price": -1.0, "sale_date": "", "market_value": 272900.0, "beds": 6.0, "bath": 2.0, "sqft": 2040.0, "year_built": "1930", "acres": 0.09}, {"parcel_id": "43503", "address": "204 28TH ST", "lat": "36.24715", "lon": "-86.637966", "sale_price": -1.0, "sale_date": "", "market_value": 232500.0, "beds": 2.0, "bath": 1.0, "sqft": 994.0, "year_built": "1940", "acres": 0.17}, {"parcel_id": "43841", "address": "3006 LAKESHORE DR", "lat": "36.246835", "lon": "-86.635273", "sale_price": -1.0, "sale_date": "", "market_value": 206300.0, "beds": 2.0, "bath": 1.0, "sqft": 756.0, "year_built": "1930", "acres": 0.16}, {"parcel_id": "49709", "address": "432 EWING DR", "lat": "36.231974", "lon": "-86.786231", "sale_price": -1.0, "sale_date": "", "market_value": 213300.0, "beds": 2.0, "bath": 1.0, "sqft": 925.0, "year_built": "1955", "acres": 0.8}, {"parcel_id": "53042", "address": "5032 INGLEWOOD CT", "lat": "36.233664", "lon": "-86.723339", "sale_price": -1.0, "sale_date": "", "market_value": 427800.0, "beds": 2.0, "bath": 2.0, "sqft": 1230.0, "year_built": "1950", "acres": 0.34}, {"parcel_id": "54700", "address": "539 BEN ALLEN RD", "lat": "36.219531", "lon": "-86.743127", "sale_price": -1.0, "sale_date": "", "market_value": 276200.0, "beds": 2.0, "bath": 2.0, "sqft": 810.0, "year_built": "1963", "acres": 0.43}, {"parcel_id": "54701", "address": "541 BEN ALLEN RD", "lat": "36.219403", "lon": "-86.743085", "sale_price": -1.0, "sale_date": "", "market_value": 270000.0, "beds": 2.0, "bath": 1.0, "sqft": 810.0, "year_built": "1960", "acres": 0.46}, {"parcel_id": "67655", "address": "1902 COUNTY HOSPITAL RD", "lat": "36.19233", "lon": "-86.834162", "sale_price": -1.0, "sale_date": "", "market_value": 332200.0, "beds": 3.0, "bath": 1.0, "sqft": 1300.0, "year_built": "1950", "acres": 0.64}, {"parcel_id": "67999", "address": "2230 VALLEY AVE", "lat": "36.199735", "lon": "-86.832523", "sale_price": 74000.0, "sale_date": "23 Jun 2009", "market_value": 234200.0, "beds": 2.0, "bath": 1.0, "sqft": 1071.0, "year_built": "1951", "acres": 0.68}, {"parcel_id": "68768", "address": "1818 GLADE ST", "lat": "36.203408", "lon": "-86.78469", "sale_price": -1.0, "sale_date": "", "market_value": 186000.0, "beds": 3.0, "bath": 2.0, "sqft": 1220.0, "year_built": "1960", "acres": 0.14}, {"parcel_id": "68769", "address": "1820 GLADE ST", "lat": "36.203456", "lon": "-86.784568", "sale_price": -1.0, "sale_date": "", "market_value": 189700.0, "beds": 2.0, "bath": 2.0, "sqft": 1151.0, "year_built": "1966", "acres": 0.14}, {"parcel_id": "69888", "address": "2316 WOODRIDGE DR", "lat": "36.210241", "lon": "-86.787595", "sale_price": -1.0, "sale_date": "", "market_value": 210900.0, "beds": 3.0, "bath": 1.0, "sqft": 950.0, "year_built": "1970", "acres": 0.21}, {"parcel_id": "74620", "address": "1705 EVELYN AVE", "lat": "36.203767", "lon": "-86.722305", "sale_price": -1.0, "sale_date": "", "market_value": 322800.0, "beds": 3.0, "bath": 1.0, "sqft": 748.0, "year_built": "1962", "acres": 0.16}, {"parcel_id": "75659", "address": "906 MAYNOR AVE", "lat": "36.207856", "lon": "-86.741432", "sale_price": 65000.0, "sale_date": "13 Feb 2009", "market_value": 229400.0, "beds": 2.0, "bath": 1.0, "sqft": 664.0, "year_built": "1930", "acres": 0.22}, {"parcel_id": "75904", "address": "934 ELVIRA AVE", "lat": "36.206085", "lon": "-86.740386", "sale_price": -1.0, "sale_date": "", "market_value": 317500.0, "beds": 2.0, "bath": 1.0, "sqft": 770.0, "year_built": "1970", "acres": 0.21}, {"parcel_id": "77846", "address": "1819 MARSDEN AVE", "lat": "36.200639", "lon": "-86.716799", "sale_price": -1.0, "sale_date": "", "market_value": 483000.0, "beds": 4.0, "bath": 2.0, "sqft": 1545.0, "year_built": "1960", "acres": 0.4}, {"parcel_id": "77847", "address": "1817 MARSDEN AVE", "lat": "36.200669", "lon": "-86.717233", "sale_price": -1.0, "sale_date": "", "market_value": 483200.0, "beds": 4.0, "bath": 2.0, "sqft": 1544.0, "year_built": "1960", "acres": 0.45}, {"parcel_id": "78018", "address": "1410 CHESTER AVE", "lat": "36.194438", "lon": "-86.734033", "sale_price": -1.0, "sale_date": "", "market_value": 309500.0, "beds": 2.0, "bath": 2.0, "sqft": 1152.0, "year_built": "1950", "acres": 0.17}, {"parcel_id": "80861", "address": "2617 MORGANMEADE DR", "lat": "36.201985", "lon": "-86.700309", "sale_price": -1.0, "sale_date": "", "market_value": 391000.0, "beds": 4.0, "bath": 2.0, "sqft": 1718.0, "year_built": "1983", "acres": 0.34}, {"parcel_id": "81061", "address": "1929 MORAN AVE", "lat": "36.208068", "lon": "-86.710319", "sale_price": -1.0, "sale_date": "", "market_value": 424900.0, "beds": 2.0, "bath": 1.0, "sqft": 1040.0, "year_built": "1951", "acres": 0.27}, {"parcel_id": "81886", "address": "2415 VALE LN", "lat": "36.197906", "lon": "-86.679839", "sale_price": -1.0, "sale_date": "", "market_value": 400800.0, "beds": 4.0, "bath": 2.0, "sqft": 1575.0, "year_built": "1958", "acres": 0.55}, {"parcel_id": "83660", "address": "913 OAK VALE", "lat": "36.211834", "lon": "-86.628514", "sale_price": -1.0, "sale_date": "", "market_value": 271400.0, "beds": 4.0, "bath": 2.0, "sqft": 1416.0, "year_built": "1978", "acres": 0.43}, {"parcel_id": "85248", "address": "221 BONNAFIELD DR", "lat": "36.201868", "lon": "-86.627726", "sale_price": -1.0, "sale_date": "", "market_value": 291300.0, "beds": 3.0, "bath": 1.0, "sqft": 1250.0, "year_built": "1968", "acres": 0.22}, {"parcel_id": "87285", "address": "5016 BONNASIDE DR", "lat": "36.193287", "lon": "-86.629073", "sale_price": -1.0, "sale_date": "", "market_value": 234800.0, "beds": 3.0, "bath": 1.0, "sqft": 1100.0, "year_built": "1960", "acres": 0.37}, {"parcel_id": "93064", "address": "1915 CEPHAS ST", "lat": "36.183093", "lon": "-86.807053", "sale_price": -1.0, "sale_date": "", "market_value": 197900.0, "beds": 2.0, "bath": 1.0, "sqft": 1172.0, "year_built": "1920", "acres": 0.13}, {"parcel_id": "95196", "address": "1414 ARTHUR AVE", "lat": "36.175493", "lon": "-86.797836", "sale_price": -1.0, "sale_date": "", "market_value": 433100.0, "beds": 4.0, "bath": 1.5, "sqft": 4350.0, "year_built": "1925", "acres": 0.17}, {"parcel_id": "95197", "address": "1412 ARTHUR AVE", "lat": "36.175403", "lon": "-86.797712", "sale_price": -1.0, "sale_date": "", "market_value": 355000.0, "beds": 4.0, "bath": 2.0, "sqft": 1212.0, "year_built": "1945", "acres": 0.17}, {"parcel_id": "96664", "address": "1113 STAINBACK AVE", "lat": "36.190875", "lon": "-86.764672", "sale_price": -1.0, "sale_date": "", "market_value": 469800.0, "beds": 3.0, "bath": 1.0, "sqft": 1076.0, "year_built": "1965", "acres": 0.17}, {"parcel_id": "97571", "address": "910 CHICAMAUGA AVE", "lat": "36.184946", "lon": "-86.753352", "sale_price": -1.0, "sale_date": "", "market_value": 505200.0, "beds": 2.0, "bath": 1.0, "sqft": 1308.0, "year_built": "1985", "acres": 0.17}, {"parcel_id": "97785", "address": "205 NEILL AVE", "lat": "36.178409", "lon": "-86.758663", "sale_price": -1.0, "sale_date": "", "market_value": 370600.0, "beds": 4.0, "bath": 2.0, "sqft": 1680.0, "year_built": "1979", "acres": 0.2}]}