{"cluster_id": 175, "name": "BLACKACRE DEVELOPMENT CO LLC", "entity_count": 18, "parcel_count": 50, "total_market_value": 0, "total_acres": 0.0, "owner_names": ["BLACKACRE ASSOCIATES LLC", "BLACKACRE DEVELOPMENT CO LLC", "O I C HOMES AT 1213 AND 1215 KELLER AVE", "O I C HOMES AT 1217 AND 1219 KELLER AVE", "O I C HOMES AT 1416 HUFFINE STREET", "O I C HOMES AT 18 CLAIBORNE STREET 1", "O I C HOMES AT 18 CLAIBORNE STREET II", "O I C HOMES AT 1802 NASSAU STREET", "O I C HOMES AT 2219 SADLER AVENUE", "O I C HOMES AT 3514 3516 WILBUR AMEND", "O I C HOMES AT 625 RIES AVENUE", "O I C HOMES AT 750 CROLEY", "O I C HOMES AT HILLSIDE AND 10TH", "O I C HOMES AT SADLER AND GLENROSE", "O I C HOMES ON KELLER AVENUE", "O I C HOMES ON ROSEMARY LANE", "O I C HOMES ON SADLER AVENUE", "O I C HOMES ON WHITNEY AVENUE"], "registered_agents": [], "principal_offices": [], "primary_sos_status": "", "primary_foreign_state": "", "brand": "", "opencorporates": "https://opencorporates.com/companies?q=BLACKACRE+DEVELOPMENT+CO+LLC&utf8=%E2%9C%93", "primary_type": "", "portfolio": {"n_parcels_with_acs": 13, "median_income": 85788, "median_home_value": 489111, "pct_renter": 47, "pct_poverty": null, "pct_vacant": 11, "pct_black": 23, "pct_white": 53, "pct_hispanic": 18, "pct_asian": 2}, "related": [{"owner": "BLACKACRE ASSOCIATES LLC", "parcels": 4, "via": "mailing address"}, {"owner": "O I C HOMES AT 1802 NASSAU STREET", "parcels": 1, "via": "mailing address"}, {"owner": "O I C HOMES AT 1217 AND 1219 KELLER AVE", "parcels": 1, "via": "mailing address"}, {"owner": "O I C HOMES AT 1416 HUFFINE STREET", "parcels": 1, "via": "mailing address"}, {"owner": "O I C HOMES AT 18 CLAIBORNE STREET 1", "parcels": 1, "via": "mailing address"}, {"owner": "O I C HOMES AT 18 CLAIBORNE STREET II", "parcels": 1, "via": "mailing address"}, {"owner": "O I C HOMES AT 625 RIES AVENUE", "parcels": 1, "via": "mailing address"}, {"owner": "O I C HOMES AT HILLSIDE AND 10TH", "parcels": 1, "via": "mailing address"}, {"owner": "O I C HOMES ON SADLER AVENUE", "parcels": 1, "via": "mailing address"}, {"owner": "O I C HOMES ON ROSEMARY LANE", "parcels": 1, "via": "mailing address"}, {"owner": "O I C HOMES ON WHITNEY AVENUE", "parcels": 1, "via": "mailing address"}, {"owner": "O I C HOMES AT 3514 3516 WILBUR AMEND", "parcels": 1, "via": "mailing address"}, {"owner": "O I C HOMES AT 750 CROLEY", "parcels": 1, "via": "mailing address"}, {"owner": "O I C HOMES ON KELLER AVENUE", "parcels": 1, "via": "mailing address"}, {"owner": "O I C HOMES AT 2219 SADLER AVENUE", "parcels": 1, "via": "mailing address"}, {"owner": "O I C HOMES AT 1213 AND 1215 KELLER AVE", "parcels": 1, "via": "mailing address"}, {"owner": "O I C HOMES AT SADLER AND GLENROSE", "parcels": 1, "via": "mailing address"}], "parcels": [{"parcel_id": "114141", "address": "", "lat": "", "lon": ""}, {"parcel_id": "115012", "address": "", "lat": "", "lon": ""}, {"parcel_id": "116310", "address": "", "lat": "", "lon": ""}, {"parcel_id": "116311", "address": "", "lat": "", "lon": ""}, {"parcel_id": "117071", "address": "", "lat": "", "lon": ""}, {"parcel_id": "118052", "address": "", "lat": "", "lon": ""}, {"parcel_id": "118053", "address": "", "lat": "", "lon": ""}, {"parcel_id": "119487", "address": "", "lat": "", "lon": ""}, {"parcel_id": "119586", "address": "", "lat": "", "lon": ""}, {"parcel_id": "163070", "address": "", "lat": "", "lon": ""}, {"parcel_id": "164015", "address": "", "lat": "", "lon": ""}, {"parcel_id": "165672", "address": "", "lat": "", "lon": ""}, {"parcel_id": "165673", "address": "", "lat": "", "lon": ""}, {"parcel_id": "167494", "address": "", "lat": "", "lon": ""}, {"parcel_id": "167512", "address": "", "lat": "", "lon": ""}, {"parcel_id": "192171", "address": "", "lat": "", "lon": ""}, {"parcel_id": "192205", "address": "", "lat": "", "lon": ""}, {"parcel_id": "192207", "address": "", "lat": "", "lon": ""}, {"parcel_id": "192214", "address": "", "lat": "", "lon": ""}, {"parcel_id": "421751", "address": "20 CLAIBORNE ST", "lat": "36.147563", "lon": "-86.761709"}, {"parcel_id": "421754", "address": "18 CLAIBORNE ST", "lat": "36.147456", "lon": "-86.761731"}, {"parcel_id": "422726", "address": "", "lat": "", "lon": ""}, {"parcel_id": "432890", "address": "625C RIES AVE", "lat": "36.159571", "lon": "-86.873547"}, {"parcel_id": "438035", "address": "", "lat": "", "lon": ""}, {"parcel_id": "440189", "address": "1223B KELLER AVE", "lat": "36.203634", "lon": "-86.732892"}, {"parcel_id": "440206", "address": "1804C NASSAU ST", "lat": "36.18225", "lon": "-86.798498"}, {"parcel_id": "440678", "address": "2212B SADLER AVE", "lat": "36.124662", "lon": "-86.747943"}, {"parcel_id": "441773", "address": "2141C ROSEMARY LN", "lat": "36.127052", "lon": "-86.750567"}, {"parcel_id": "442234", "address": "1215B KELLER AVE", "lat": "36.203684", "lon": "-86.733379"}, {"parcel_id": "442237", "address": "1219B KELLER AVE", "lat": "36.203664", "lon": "-86.733169"}, {"parcel_id": "444109", "address": "2164B WHITNEY AVE", "lat": "36.126079", "lon": "-86.751188"}, {"parcel_id": "449761", "address": "", "lat": "", "lon": ""}, {"parcel_id": "449762", "address": "", "lat": "", "lon": ""}, {"parcel_id": "451725", "address": "1416 C HUFFINE ST", "lat": "36.202421", "lon": "-86.730944"}, {"parcel_id": "452635", "address": "3516B WILBUR PL", "lat": "36.108823", "lon": "-86.782471"}, {"parcel_id": "453941", "address": "1710B 10TH AVE S", "lat": "36.136699", "lon": "-86.78385"}, {"parcel_id": "458472", "address": "2219C SADLER AVE", "lat": "36.124282", "lon": "-86.748862"}, {"parcel_id": "461770", "address": "2200 SADLER AVE", "lat": "36.125507", "lon": "-86.74793"}, {"parcel_id": "461771", "address": "319 GLENROSE AVE", "lat": "36.125499", "lon": "-86.747756"}, {"parcel_id": "461772", "address": "319B GLENROSE AVE", "lat": "36.125533", "lon": "-86.747853"}, {"parcel_id": "461775", "address": "750 CROLEY DR", "lat": "36.16094", "lon": "-86.873992"}, {"parcel_id": "75078", "address": "", "lat": "", "lon": ""}, {"parcel_id": "75084", "address": "", "lat": "", "lon": ""}, {"parcel_id": "75092", "address": "", "lat": "", "lon": ""}, {"parcel_id": "76762", "address": "", "lat": "", "lon": ""}, {"parcel_id": "77180", "address": "", "lat": "", "lon": ""}, {"parcel_id": "78845", "address": "", "lat": "", "lon": ""}, {"parcel_id": "89961", "address": "", "lat": "", "lon": ""}, {"parcel_id": "89978", "address": "", "lat": "", "lon": ""}, {"parcel_id": "92975", "address": "", "lat": "", "lon": ""}]}