{"cluster_id": 1853, "name": "UMG RECORDINGS INC", "entity_count": 1, "parcel_count": 7, "total_market_value": 12508200, "total_acres": 1.9, "owner_names": ["UMG RECORDINGS INC"], "registered_agents": ["C T CORPORATION SYSTEM"], "principal_offices": ["2220 COLORADO AVE, SANTA MONICA, CA 90404"], "primary_sos_status": "", "primary_foreign_state": "", "brand": "", "opencorporates": "https://opencorporates.com/companies?q=UMG+RECORDINGS+INC&utf8=%E2%9C%93", "primary_type": "", "portfolio": {"n_parcels_with_acs": 7, "median_income": 90417, "median_home_value": 625000, "pct_renter": 62, "pct_poverty": null, "pct_vacant": 16, "pct_black": 14, "pct_white": 77, "pct_hispanic": 5, "pct_asian": 1}, "related": [], "parcels": [{"parcel_id": "188481", "address": "2801 COLUMBINE PL", "lat": "36.116392", "lon": "-86.765598", "sale_price": 650382.0, "sale_date": "16 Nov 2018", "market_value": 1963200.0, "beds": 0.0, "bath": 0.0, "sqft": 1245.0, "year_built": "1975", "acres": 0.29}, {"parcel_id": "188593", "address": "2800 COLUMBINE PL", "lat": "36.116069", "lon": "-86.76461", "sale_price": 391447.0, "sale_date": "16 Nov 2018", "market_value": 1039800.0, "beds": 0.0, "bath": 0.0, "sqft": 986.0, "year_built": "1975", "acres": 0.18}, {"parcel_id": "188594", "address": "517 E IRIS DR", "lat": "36.116287", "lon": "-86.764564", "sale_price": -1.0, "sale_date": "", "market_value": 1644500.0, "beds": 2.0, "bath": 0.0, "sqft": 2879.0, "year_built": "2015", "acres": 0.26}, {"parcel_id": "188595", "address": "515 E IRIS DR", "lat": "36.116235", "lon": "-86.764185", "sale_price": 1985000.0, "sale_date": "16 Jun 2025", "market_value": 1798600.0, "beds": 0.0, "bath": 0.0, "sqft": 2280.0, "year_built": "1980", "acres": 0.23}, {"parcel_id": "188708", "address": "520 E IRIS DR", "lat": "36.11677", "lon": "-86.764798", "sale_price": 187000.0, "sale_date": "19 Jun 2009", "market_value": 1296000.0, "beds": 0.0, "bath": 0.0, "sqft": 1130.0, "year_built": "1975", "acres": 0.21}, {"parcel_id": "188709", "address": "518 E IRIS DR", "lat": "36.116736", "lon": "-86.764448", "sale_price": -1.0, "sale_date": "", "market_value": 3187700.0, "beds": 0.0, "bath": 0.0, "sqft": 9027.0, "year_built": "1997", "acres": 0.43}, {"parcel_id": "188711", "address": "514 E IRIS DR", "lat": "36.116713", "lon": "-86.764057", "sale_price": 615000.0, "sale_date": "22 Dec 2017", "market_value": 1578400.0, "beds": 0.0, "bath": 0.0, "sqft": 1710.0, "year_built": "1975", "acres": 0.27}]}