{"cluster_id": 1910, "name": "HELLER INVESTMENTS LLC", "entity_count": 5, "parcel_count": 6, "total_market_value": 1100100, "total_acres": 0.3, "owner_names": ["621 BELGIUM DRIVE LLC", "HELLER FAMILY LIVING TRUST", "HELLER INVESTMENTS LLC", "O I C HOMES AT 1033 MONROE STREET", "SOUTHERN COMFORT HOMES LLC"], "registered_agents": [], "principal_offices": [], "primary_sos_status": "", "primary_foreign_state": "", "brand": "", "opencorporates": "https://opencorporates.com/companies?q=HELLER+INVESTMENTS+LLC&utf8=%E2%9C%93", "primary_type": "", "portfolio": {"n_parcels_with_acs": 3, "median_income": 73111, "median_home_value": 532467, "pct_renter": 55, "pct_poverty": null, "pct_vacant": 13, "pct_black": 50, "pct_white": 46, "pct_hispanic": 4, "pct_asian": 1}, "related": [{"owner": "621 BELGIUM DRIVE LLC", "parcels": 1, "via": "mailing address"}, {"owner": "SOUTHERN COMFORT HOMES LLC", "parcels": 1, "via": "mailing address"}, {"owner": "O I C HOMES AT 1033 MONROE STREET", "parcels": 1, "via": "mailing address"}, {"owner": "HELLER FAMILY LIVING TRUST", "parcels": 1, "via": "mailing address"}], "parcels": [{"parcel_id": "147164", "address": "", "lat": "", "lon": ""}, {"parcel_id": "429698", "address": "1033C MONROE ST", "lat": "36.173521", "lon": "-86.79828"}, {"parcel_id": "431692", "address": "1029A MONROE ST", "lat": "36.173579", "lon": "-86.798019", "sale_price": -1.0, "sale_date": "", "market_value": 779700.0, "beds": 3.0, "bath": 3.0, "sqft": 2228.0, "year_built": "2019", "acres": null}, {"parcel_id": "86554", "address": "621 BELGIUM DR", "lat": "36.202639", "lon": "-86.598951", "sale_price": 210000.0, "sale_date": "25 Sep 2017", "market_value": 320400.0, "beds": 4.0, "bath": 4.0, "sqft": 1980.0, "year_built": "1984", "acres": 0.32}, {"parcel_id": "93828", "address": "", "lat": "", "lon": ""}, {"parcel_id": "93829", "address": "", "lat": "", "lon": ""}]}