{"cluster_id": 259, "name": "M I HOMES OF NASHVILLE LLC", "entity_count": 1, "parcel_count": 35, "total_market_value": 479600, "total_acres": 4.0, "owner_names": ["M I HOMES OF NASHVILLE LLC"], "registered_agents": [], "principal_offices": [], "primary_sos_status": "", "primary_foreign_state": "", "brand": "", "opencorporates": "https://opencorporates.com/companies?q=M+I+HOMES+OF+NASHVILLE+LLC&utf8=%E2%9C%93", "primary_type": "", "portfolio": {"n_parcels_with_acs": 34, "median_income": 76019, "median_home_value": 306250, "pct_renter": 13, "pct_poverty": null, "pct_vacant": 14, "pct_black": 25, "pct_white": 57, "pct_hispanic": 9, "pct_asian": 0}, "related": [], "parcels": [{"parcel_id": "142077", "address": "5047 JOHN HAGAR RD", "lat": "36.155758", "lon": "-86.58223"}, {"parcel_id": "142325", "address": "0 JOHN HAGAR RD", "lat": "36.154628", "lon": "-86.582385"}, {"parcel_id": "281255", "address": "0 HAMILTON CHURCH RD", "lat": "36.052355", "lon": "-86.581886"}, {"parcel_id": "281258", "address": "3817 HAMILTON CHURCH RD", "lat": "36.054127", "lon": "-86.580847", "sale_price": -1.0, "sale_date": "", "market_value": 479600.0, "beds": 2.0, "bath": 1.0, "sqft": 760.0, "year_built": "1945", "acres": 3.97}, {"parcel_id": "283635", "address": "3807 HAMILTON CHURCH RD", "lat": "36.054647", "lon": "-86.581146"}, {"parcel_id": "474653", "address": "500 CANAL CIR", "lat": "36.232366", "lon": "-86.698453"}, {"parcel_id": "474654", "address": "504 CANAL CIR", "lat": "36.232249", "lon": "-86.698486"}, {"parcel_id": "474656", "address": "512 CANAL CIR", "lat": "36.232018", "lon": "-86.698553"}, {"parcel_id": "474657", "address": "516 CANAL CIR", "lat": "36.231879", "lon": "-86.698598"}, {"parcel_id": "474658", "address": "914 WATERCOURSE CT", "lat": "36.232111", "lon": "-86.699059"}, {"parcel_id": "474660", "address": "922 WATERCOURSE CT", "lat": "36.232333", "lon": "-86.699206"}, {"parcel_id": "474663", "address": "934 WATERCOURSE CT", "lat": "36.232685", "lon": "-86.699445"}, {"parcel_id": "474664", "address": "938 WATERCOURSE CT", "lat": "36.232828", "lon": "-86.699412"}, {"parcel_id": "474665", "address": "942 WATERCOURSE CT", "lat": "36.232899", "lon": "-86.69917"}, {"parcel_id": "474666", "address": "965 WATERCOURSE CT", "lat": "36.233495", "lon": "-86.699654"}, {"parcel_id": "474667", "address": "961 WATERCOURSE CT", "lat": "36.233397", "lon": "-86.69977"}, {"parcel_id": "474668", "address": "957 WATERCOURSE CT", "lat": "36.233285", "lon": "-86.699836"}, {"parcel_id": "474669", "address": "953 WATERCOURSE CT", "lat": "36.233183", "lon": "-86.699917"}, {"parcel_id": "474670", "address": "949 WATERCOURSE CT", "lat": "36.233069", "lon": "-86.699988"}, {"parcel_id": "474671", "address": "945 WATERCOURSE CT", "lat": "36.23295", "lon": "-86.70006"}, {"parcel_id": "474672", "address": "937 WATERCOURSE CT", "lat": "36.232288", "lon": "-86.700038"}, {"parcel_id": "474673", "address": "933 WATERCOURSE CT", "lat": "36.232175", "lon": "-86.699944"}, {"parcel_id": "474674", "address": "929 WATERCOURSE CT", "lat": "36.232077", "lon": "-86.699843"}, {"parcel_id": "474675", "address": "925 WATERCOURSE CT", "lat": "36.231987", "lon": "-86.699752"}, {"parcel_id": "474676", "address": "921 WATERCOURSE CT", "lat": "36.231896", "lon": "-86.699669"}, {"parcel_id": "474677", "address": "917 WATERCOURSE CT", "lat": "36.231809", "lon": "-86.699581"}, {"parcel_id": "474678", "address": "913 WATERCOURSE CT", "lat": "36.231725", "lon": "-86.699485"}, {"parcel_id": "474679", "address": "909 WATERCOURSE CT", "lat": "36.231647", "lon": "-86.699381"}, {"parcel_id": "474680", "address": "557 CANAL CIR", "lat": "36.231415", "lon": "-86.699208"}, {"parcel_id": "474681", "address": "553 CANAL CIR", "lat": "36.231288", "lon": "-86.699145"}, {"parcel_id": "474685", "address": "537 CANAL CIR", "lat": "36.231144", "lon": "-86.698403"}, {"parcel_id": "474694", "address": "501 CANAL CIR", "lat": "36.232196", "lon": "-86.69789"}, {"parcel_id": "474695", "address": "901 WATERCOURSE CT", "lat": "36.231565", "lon": "-86.698671"}, {"parcel_id": "474696", "address": "906 WATERCOURSE CT", "lat": "36.232318", "lon": "-86.700325"}, {"parcel_id": "58037", "address": "", "lat": "", "lon": ""}]}