{"cluster_id": 2647, "name": "NGUYEN MAI REVOCABLE LIVING TRUST", "entity_count": 1, "parcel_count": 5, "total_market_value": 1873600, "total_acres": 0.4, "owner_names": ["NGUYEN MAI REVOCABLE LIVING TRUST"], "registered_agents": [], "principal_offices": [], "primary_sos_status": "", "primary_foreign_state": "", "brand": "", "opencorporates": "https://opencorporates.com/companies?q=NGUYEN+MAI+REVOCABLE+LIVING+TRUST&utf8=%E2%9C%93", "primary_type": "", "portfolio": {"n_parcels_with_acs": 5, "median_income": 76421, "median_home_value": 322880, "pct_renter": 27, "pct_poverty": null, "pct_vacant": 4, "pct_black": 30, "pct_white": 39, "pct_hispanic": 33, "pct_asian": 3}, "related": [], "parcels": [{"parcel_id": "250271", "address": "1912 TERRAGON CT", "lat": "36.075684", "lon": "-86.66998", "sale_price": -1.0, "sale_date": "", "market_value": 302500.0, "beds": 3.0, "bath": 2.5, "sqft": 1329.0, "year_built": "2006", "acres": null}, {"parcel_id": "252436", "address": "2913 SPLIT OAK TRL", "lat": "36.077996", "lon": "-86.651426", "sale_price": 161900.0, "sale_date": "28 Oct 2016", "market_value": 346800.0, "beds": 3.0, "bath": 2.0, "sqft": 1188.0, "year_built": "1997", "acres": 0.18}, {"parcel_id": "283349", "address": "2201 GREEN TRAILS DR", "lat": "36.041159", "lon": "-86.701228", "sale_price": -1.0, "sale_date": "", "market_value": 437800.0, "beds": 3.0, "bath": 2.5, "sqft": 1882.0, "year_built": "2004", "acres": null}, {"parcel_id": "286924", "address": "560 CEDARMONT DR", "lat": "36.034399", "lon": "-86.707058", "sale_price": -1.0, "sale_date": "", "market_value": 406500.0, "beds": 3.0, "bath": 2.0, "sqft": 1463.0, "year_built": "1980", "acres": 0.23}, {"parcel_id": "362531", "address": "605 SOUTHBEACH CV", "lat": "36.05495", "lon": "-86.58835", "sale_price": 204990.0, "sale_date": "31 Jan 2017", "market_value": 380000.0, "beds": 4.0, "bath": 2.0, "sqft": 1813.0, "year_built": "2016", "acres": null}]}