{"cluster_id": 3635, "name": "WMCI NASHVILLE VIII A LLC ET AL", "entity_count": 3, "parcel_count": 4, "total_market_value": 133531000, "total_acres": 8.2, "owner_names": ["WMCI NASHVILLE III LLC WMCI NASHVILLE III B LLC", "WMCI NASHVILLE VII LLC WMCI NASHVILLE VII B LLC", "WMCI NASHVILLE VIII A LLC ET AL"], "registered_agents": [], "principal_offices": [], "primary_sos_status": "", "primary_foreign_state": "", "brand": "", "opencorporates": "https://opencorporates.com/companies?q=WMCI+NASHVILLE+VIII+A+LLC+ET+AL&utf8=%E2%9C%93", "primary_type": "", "portfolio": {"n_parcels_with_acs": 4, "median_income": 78954, "median_home_value": 507350, "pct_renter": 79, "pct_poverty": null, "pct_vacant": 16, "pct_black": 8, "pct_white": 84, "pct_hispanic": 4, "pct_asian": 3}, "related": [{"owner": "WMCI NASHVILLE III LLC WMCI NASHVILLE III B LLC", "parcels": 1, "via": "mailing address"}, {"owner": "WMCI NASHVILLE VII LLC WMCI NASHVILLE VII B LLC", "parcels": 1, "via": "mailing address"}], "parcels": [{"parcel_id": "100283", "address": "211 STOCKYARD ST", "lat": "36.172069", "lon": "-86.782142", "sale_price": -1.0, "sale_date": "", "market_value": 46175400.0, "beds": 0.0, "bath": 0.0, "sqft": 0.0, "year_built": "2020", "acres": 1.6}, {"parcel_id": "115931", "address": "1720 61ST AVE N", "lat": "36.167915", "lon": "-86.85619"}, {"parcel_id": "115940", "address": "5500 CENTENNIAL BLVD", "lat": "36.166405", "lon": "-86.854767", "sale_price": 56500000.0, "sale_date": "21 Aug 2021", "market_value": 39531000.0, "beds": 0.0, "bath": 0.0, "sqft": 0.0, "year_built": "2018", "acres": 5.1}, {"parcel_id": "99902", "address": "210 STOCKYARD ST", "lat": "36.17283", "lon": "-86.782588", "sale_price": -1.0, "sale_date": "", "market_value": 47824600.0, "beds": 0.0, "bath": 0.0, "sqft": 0.0, "year_built": "2015", "acres": 1.52}]}