{"cluster_id": 38, "name": "KLLB AIV LLC", "entity_count": 1, "parcel_count": 142, "total_market_value": 0, "total_acres": 0.0, "owner_names": ["KLLB AIV LLC"], "registered_agents": ["COGENCY GLOBAL INC."], "principal_offices": ["225 LIBERTY STREET SUITE 4210, NEW YORK, NY 10281"], "primary_sos_status": "", "primary_foreign_state": "", "brand": "", "opencorporates": "https://opencorporates.com/companies?q=KLLB+AIV+LLC&utf8=%E2%9C%93", "primary_type": "", "portfolio": {"n_parcels_with_acs": 141, "median_income": 52959, "median_home_value": 489800, "pct_renter": 62, "pct_poverty": null, "pct_vacant": 21, "pct_black": 6, "pct_white": 71, "pct_hispanic": 12, "pct_asian": 0}, "related": [], "parcels": [{"parcel_id": "469555", "address": "", "lat": "", "lon": ""}, {"parcel_id": "472522", "address": "3 LUCILE ST", "lat": "36.196938", "lon": "-86.774938"}, {"parcel_id": "472523", "address": "5 LUCILE ST", "lat": "36.196938", "lon": "-86.77487"}, {"parcel_id": "472524", "address": "7 LUCILE ST", "lat": "36.196938", "lon": "-86.774804"}, {"parcel_id": "472525", "address": "9 LUCILE ST", "lat": "36.196938", "lon": "-86.774735"}, {"parcel_id": "472526", "address": "13 LUCILE ST", "lat": "36.196939", "lon": "-86.774555"}, {"parcel_id": "472527", "address": "15 LUCILE ST", "lat": "36.196939", "lon": "-86.774483"}, {"parcel_id": "472528", "address": "17 LUCILE ST", "lat": "36.196939", "lon": "-86.774418"}, {"parcel_id": "472571", "address": "301 LYRIC ALY", "lat": "36.19787", "lon": "-86.774081"}, {"parcel_id": "472572", "address": "300 LYRIC ALY", "lat": "36.198059", "lon": "-86.774022"}, {"parcel_id": "472573", "address": "302 LYRIC ALY", "lat": "36.198072", "lon": "-86.774086"}, {"parcel_id": "472574", "address": "304 LYRIC ALY", "lat": "36.198086", "lon": "-86.774151"}, {"parcel_id": "472575", "address": "306 LYRIC ALY", "lat": "36.1981", "lon": "-86.774218"}, {"parcel_id": "472576", "address": "308 LYRIC ALY", "lat": "36.198114", "lon": "-86.774287"}, {"parcel_id": "472577", "address": "310 LYRIC ALY", "lat": "36.198143", "lon": "-86.774408"}, {"parcel_id": "472578", "address": "312 LYRIC ALY", "lat": "36.198155", "lon": "-86.774476"}, {"parcel_id": "472579", "address": "314 LYRIC ALY", "lat": "36.198168", "lon": "-86.774542"}, {"parcel_id": "472580", "address": "316 LYRIC ALY", "lat": "36.198181", "lon": "-86.774609"}, {"parcel_id": "472581", "address": "318 LYRIC ALY", "lat": "36.198203", "lon": "-86.774732"}, {"parcel_id": "472582", "address": "320 LYRIC ALY", "lat": "36.198216", "lon": "-86.774794"}, {"parcel_id": "472583", "address": "322 LYRIC ALY", "lat": "36.19823", "lon": "-86.77486"}, {"parcel_id": "472584", "address": "324 LYRIC ALY", "lat": "36.198244", "lon": "-86.774927"}, {"parcel_id": "472585", "address": "326 LYRIC ALY", "lat": "36.198257", "lon": "-86.77499"}, {"parcel_id": "472586", "address": "429 PRELUDE ALY", "lat": "36.198491", "lon": "-86.775003"}, {"parcel_id": "472587", "address": "427 PRELUDE ALY", "lat": "36.19848", "lon": "-86.774939"}, {"parcel_id": "472588", "address": "425 PRELUDE ALY", "lat": "36.198467", "lon": "-86.774875"}, {"parcel_id": "472589", "address": "423 PRELUDE ALY", "lat": "36.198454", "lon": "-86.774811"}, {"parcel_id": "472590", "address": "421 PRELUDE ALY", "lat": "36.198441", "lon": "-86.774744"}, {"parcel_id": "472591", "address": "419 PRELUDE ALY", "lat": "36.198412", "lon": "-86.774611"}, {"parcel_id": "472592", "address": "417 PRELUDE ALY", "lat": "36.198398", "lon": "-86.774544"}, {"parcel_id": "472593", "address": "415 PRELUDE ALY", "lat": "36.198385", "lon": "-86.774476"}, {"parcel_id": "472594", "address": "413 PRELUDE ALY", "lat": "36.198371", "lon": "-86.774411"}, {"parcel_id": "472595", "address": "411 PRELUDE ALY", "lat": "36.198358", "lon": "-86.774345"}, {"parcel_id": "472596", "address": "409 PRELUDE ALY", "lat": "36.198332", "lon": "-86.774216"}, {"parcel_id": "472597", "address": "407 PRELUDE ALY", "lat": "36.198319", "lon": "-86.77415"}, {"parcel_id": "472598", "address": "405 PRELUDE ALY", "lat": "36.198304", "lon": "-86.774081"}, {"parcel_id": "472599", "address": "403 PRELUDE ALY", "lat": "36.198291", "lon": "-86.774015"}, {"parcel_id": "472600", "address": "401 PRELUDE ALY", "lat": "36.198278", "lon": "-86.773951"}, {"parcel_id": "472601", "address": "500 CHORUS RD", "lat": "36.198469", "lon": "-86.773884"}, {"parcel_id": "472602", "address": "502 CHORUS RD", "lat": "36.198482", "lon": "-86.773949"}, {"parcel_id": "472603", "address": "504 CHORUS RD", "lat": "36.198495", "lon": "-86.774015"}, {"parcel_id": "472604", "address": "506 CHORUS RD", "lat": "36.198509", "lon": "-86.774081"}, {"parcel_id": "472605", "address": "508 CHORUS RD", "lat": "36.198523", "lon": "-86.774148"}, {"parcel_id": "472606", "address": "510 CHORUS RD", "lat": "36.198551", "lon": "-86.774284"}, {"parcel_id": "472607", "address": "512 CHORUS RD", "lat": "36.198563", "lon": "-86.77435"}, {"parcel_id": "472608", "address": "514 CHORUS RD", "lat": "36.198577", "lon": "-86.774417"}, {"parcel_id": "472609", "address": "516 CHORUS RD", "lat": "36.198591", "lon": "-86.774484"}, {"parcel_id": "472610", "address": "518 CHORUS RD", "lat": "36.198605", "lon": "-86.77455"}, {"parcel_id": "472611", "address": "520 CHORUS RD", "lat": "36.198618", "lon": "-86.774616"}, {"parcel_id": "472612", "address": "522 CHORUS RD", "lat": "36.198646", "lon": "-86.774755"}, {"parcel_id": "472613", "address": "524 CHORUS RD", "lat": "36.198658", "lon": "-86.774818"}, {"parcel_id": "472614", "address": "526 CHORUS RD", "lat": "36.19867", "lon": "-86.774881"}, {"parcel_id": "472615", "address": "528 CHORUS RD", "lat": "36.198684", "lon": "-86.774949"}, {"parcel_id": "472616", "address": "530 CHORUS RD", "lat": "36.198697", "lon": "-86.775015"}, {"parcel_id": "472617", "address": "1101 RHYTHM RD", "lat": "36.197722", "lon": "-86.775298"}, {"parcel_id": "472618", "address": "1103 RHYTHM RD", "lat": "36.197787", "lon": "-86.775303"}, {"parcel_id": "472619", "address": "1105 RHYTHM RD", "lat": "36.197851", "lon": "-86.775306"}, {"parcel_id": "472620", "address": "1107 RHYTHM RD", "lat": "36.197916", "lon": "-86.775309"}, {"parcel_id": "472621", "address": "1109 RHYTHM RD", "lat": "36.19798", "lon": "-86.775312"}, {"parcel_id": "472622", "address": "1111 RHYTHM RD", "lat": "36.198089", "lon": "-86.775322"}, {"parcel_id": "472623", "address": "1113 RHYTHM RD", "lat": "36.198155", "lon": "-86.775325"}, {"parcel_id": "472624", "address": "1115 RHYTHM RD", "lat": "36.198222", "lon": "-86.775328"}, {"parcel_id": "472625", "address": "1117 RHYTHM RD", "lat": "36.19829", "lon": "-86.775331"}, {"parcel_id": "472626", "address": "1119 RHYTHM RD", "lat": "36.198355", "lon": "-86.775334"}, {"parcel_id": "472627", "address": "1121 RHYTHM RD", "lat": "36.198458", "lon": "-86.775347"}, {"parcel_id": "472628", "address": "1123 RHYTHM RD", "lat": "36.198525", "lon": "-86.775349"}, {"parcel_id": "472629", "address": "1125 RHYTHM RD", "lat": "36.19859", "lon": "-86.775351"}, {"parcel_id": "472630", "address": "1127 RHYTHM RD", "lat": "36.198652", "lon": "-86.775352"}, {"parcel_id": "472631", "address": "1129 RHYTHM RD", "lat": "36.19872", "lon": "-86.775354"}, {"parcel_id": "472632", "address": "1133 RHYTHM RD", "lat": "36.198916", "lon": "-86.775288"}, {"parcel_id": "472633", "address": "1135 RHYTHM RD", "lat": "36.198979", "lon": "-86.775266"}, {"parcel_id": "472634", "address": "1137 RHYTHM RD", "lat": "36.199042", "lon": "-86.775246"}, {"parcel_id": "472635", "address": "1139 RHYTHM RD", "lat": "36.199104", "lon": "-86.775225"}, {"parcel_id": "472636", "address": "1141 RHYTHM RD", "lat": "36.199167", "lon": "-86.775204"}, {"parcel_id": "472637", "address": "1143 RHYTHM RD", "lat": "36.199232", "lon": "-86.775182"}, {"parcel_id": "472638", "address": "1145 RHYTHM RD", "lat": "36.199336", "lon": "-86.775145"}, {"parcel_id": "472639", "address": "1147 RHYTHM RD", "lat": "36.1994", "lon": "-86.775126"}, {"parcel_id": "472640", "address": "1149 RHYTHM RD", "lat": "36.199467", "lon": "-86.775107"}, {"parcel_id": "472641", "address": "1151 RHYTHM RD", "lat": "36.199532", "lon": "-86.775087"}, {"parcel_id": "472642", "address": "1153 RHYTHM RD", "lat": "36.199595", "lon": "-86.775069"}, {"parcel_id": "472643", "address": "1155 RHYTHM RD", "lat": "36.19966", "lon": "-86.775049"}, {"parcel_id": "472644", "address": "1160 RHYTHM RD", "lat": "36.199669", "lon": "-86.774682"}, {"parcel_id": "472645", "address": "1158 RHYTHM RD", "lat": "36.199616", "lon": "-86.774696"}, {"parcel_id": "472646", "address": "1156 RHYTHM RD", "lat": "36.199561", "lon": "-86.774712"}, {"parcel_id": "472647", "address": "1154 RHYTHM RD", "lat": "36.199507", "lon": "-86.774728"}, {"parcel_id": "472648", "address": "1152 RHYTHM RD", "lat": "36.199413", "lon": "-86.774758"}, {"parcel_id": "472649", "address": "1150 RHYTHM RD", "lat": "36.19936", "lon": "-86.774775"}, {"parcel_id": "472650", "address": "1148 RHYTHM RD", "lat": "36.199303", "lon": "-86.774793"}, {"parcel_id": "472651", "address": "1146 RHYTHM RD", "lat": "36.199246", "lon": "-86.774812"}, {"parcel_id": "472652", "address": "1144 RHYTHM RD", "lat": "36.199196", "lon": "-86.774827"}, {"parcel_id": "472653", "address": "1142 RHYTHM RD", "lat": "36.199104", "lon": "-86.774854"}, {"parcel_id": "472654", "address": "1140 RHYTHM RD", "lat": "36.19905", "lon": "-86.774871"}, {"parcel_id": "472655", "address": "1138 RHYTHM RD", "lat": "36.198998", "lon": "-86.774888"}, {"parcel_id": "472656", "address": "1136 RHYTHM RD", "lat": "36.198944", "lon": "-86.774905"}, {"parcel_id": "472657", "address": "900 BALLARD ALY", "lat": "36.198897", "lon": "-86.774669"}, {"parcel_id": "472658", "address": "902 BALLARD ALY", "lat": "36.198951", "lon": "-86.774652"}, {"parcel_id": "472659", "address": "904 BALLARD ALY", "lat": "36.199004", "lon": "-86.774636"}, {"parcel_id": "472660", "address": "906 BALLARD ALY", "lat": "36.199057", "lon": "-86.774619"}, {"parcel_id": "472661", "address": "908 BALLARD ALY", "lat": "36.199151", "lon": "-86.774593"}, {"parcel_id": "472662", "address": "910 BALLARD ALY", "lat": "36.199204", "lon": "-86.774576"}, {"parcel_id": "472663", "address": "912 BALLARD ALY", "lat": "36.199257", "lon": "-86.774558"}, {"parcel_id": "472664", "address": "914 BALLARD ALY", "lat": "36.199309", "lon": "-86.774542"}, {"parcel_id": "472665", "address": "916 BALLARD ALY", "lat": "36.199363", "lon": "-86.774524"}, {"parcel_id": "472666", "address": "918 BALLARD ALY", "lat": "36.199456", "lon": "-86.774494"}, {"parcel_id": "472667", "address": "920 BALLARD ALY", "lat": "36.19951", "lon": "-86.774478"}, {"parcel_id": "472668", "address": "922 BALLARD ALY", "lat": "36.199562", "lon": "-86.774462"}, {"parcel_id": "472669", "address": "924 BALLARD ALY", "lat": "36.199616", "lon": "-86.774446"}, {"parcel_id": "472670", "address": "625 ENCORE ALY", "lat": "36.199491", "lon": "-86.773834"}, {"parcel_id": "472671", "address": "623 ENCORE ALY", "lat": "36.199438", "lon": "-86.773852"}, {"parcel_id": "472672", "address": "621 ENCORE ALY", "lat": "36.199387", "lon": "-86.773869"}, {"parcel_id": "472673", "address": "619 ENCORE ALY", "lat": "36.199333", "lon": "-86.773887"}, {"parcel_id": "472674", "address": "617 ENCORE ALY", "lat": "36.199239", "lon": "-86.773918"}, {"parcel_id": "472675", "address": "615 ENCORE ALY", "lat": "36.199187", "lon": "-86.773933"}, {"parcel_id": "472676", "address": "613 ENCORE ALY", "lat": "36.199136", "lon": "-86.773948"}, {"parcel_id": "472677", "address": "611 ENCORE ALY", "lat": "36.199082", "lon": "-86.773965"}, {"parcel_id": "472678", "address": "609 ENCORE ALY", "lat": "36.199027", "lon": "-86.773982"}, {"parcel_id": "472679", "address": "607 ENCORE ALY", "lat": "36.19893", "lon": "-86.77401"}, {"parcel_id": "472680", "address": "605 ENCORE ALY", "lat": "36.198878", "lon": "-86.774026"}, {"parcel_id": "472681", "address": "603 ENCORE ALY", "lat": "36.198826", "lon": "-86.774043"}, {"parcel_id": "472682", "address": "601 ENCORE ALY", "lat": "36.198772", "lon": "-86.77406"}, {"parcel_id": "472683", "address": "801 CADENCE ROW", "lat": "36.198726", "lon": "-86.773825"}, {"parcel_id": "472684", "address": "803 CADENCE ROW", "lat": "36.198779", "lon": "-86.773809"}, {"parcel_id": "472685", "address": "805 CADENCE ROW", "lat": "36.198831", "lon": "-86.773792"}, {"parcel_id": "472686", "address": "807 CADENCE ROW", "lat": "36.198885", "lon": "-86.773776"}, {"parcel_id": "472687", "address": "809 CADENCE ROW", "lat": "36.198977", "lon": "-86.773745"}, {"parcel_id": "472688", "address": "811 CADENCE ROW", "lat": "36.199028", "lon": "-86.77373"}, {"parcel_id": "472689", "address": "813 CADENCE ROW", "lat": "36.199083", "lon": "-86.773713"}, {"parcel_id": "472690", "address": "815 CADENCE ROW", "lat": "36.199136", "lon": "-86.773697"}, {"parcel_id": "472691", "address": "817 CADENCE ROW", "lat": "36.19919", "lon": "-86.77368"}, {"parcel_id": "472692", "address": "819 CADENCE ROW", "lat": "36.199283", "lon": "-86.773649"}, {"parcel_id": "472693", "address": "821 CADENCE ROW", "lat": "36.199335", "lon": "-86.773632"}, {"parcel_id": "472694", "address": "823 CADENCE ROW", "lat": "36.199388", "lon": "-86.773615"}, {"parcel_id": "472695", "address": "825 CADENCE ROW", "lat": "36.19944", "lon": "-86.773598"}, {"parcel_id": "472696", "address": "1211 VERSE RD", "lat": "36.199531", "lon": "-86.774039"}, {"parcel_id": "472697", "address": "1213 VERSE RD", "lat": "36.199545", "lon": "-86.774105"}, {"parcel_id": "472698", "address": "1215 VERSE RD", "lat": "36.199558", "lon": "-86.774171"}, {"parcel_id": "472699", "address": "1217 VERSE RD", "lat": "36.199572", "lon": "-86.774236"}, {"parcel_id": "472700", "address": "1208 VERSE RD", "lat": "36.199716", "lon": "-86.77382"}, {"parcel_id": "472701", "address": "1206 VERSE RD", "lat": "36.199699", "lon": "-86.773739"}, {"parcel_id": "472702", "address": "1204 VERSE RD", "lat": "36.199682", "lon": "-86.773657"}, {"parcel_id": "472703", "address": "1202 VERSE RD", "lat": "36.199666", "lon": "-86.773577"}, {"parcel_id": "472704", "address": "1200 VERSE RD", "lat": "36.199649", "lon": "-86.773495"}]}