{"cluster_id": 449, "name": "MCEWEN DEVELOPMENT LLC", "entity_count": 2, "parcel_count": 22, "total_market_value": 0, "total_acres": 0.0, "owner_names": ["LENOX VILLAGE III LLC", "MCEWEN DEVELOPMENT LLC"], "registered_agents": [], "principal_offices": [], "primary_sos_status": "", "primary_foreign_state": "", "brand": "", "opencorporates": "https://opencorporates.com/companies?q=MCEWEN+DEVELOPMENT+LLC&utf8=%E2%9C%93", "primary_type": "", "portfolio": {"n_parcels_with_acs": 1, "median_income": 50506, "median_home_value": 522200, "pct_renter": 78, "pct_poverty": null, "pct_vacant": 11, "pct_black": 25, "pct_white": 51, "pct_hispanic": 7, "pct_asian": 7}, "related": [{"owner": "LENOX VILLAGE III LLC", "parcels": 8, "via": "mailing address"}], "parcels": [{"parcel_id": "223418", "address": "", "lat": "", "lon": ""}, {"parcel_id": "225040", "address": "", "lat": "", "lon": ""}, {"parcel_id": "226221", "address": "", "lat": "", "lon": ""}, {"parcel_id": "226227", "address": "", "lat": "", "lon": ""}, {"parcel_id": "226456", "address": "", "lat": "", "lon": ""}, {"parcel_id": "226460", "address": "", "lat": "", "lon": ""}, {"parcel_id": "285664", "address": "", "lat": "", "lon": ""}, {"parcel_id": "285670", "address": "", "lat": "", "lon": ""}, {"parcel_id": "286148", "address": "", "lat": "", "lon": ""}, {"parcel_id": "286151", "address": "", "lat": "", "lon": ""}, {"parcel_id": "287130", "address": "", "lat": "", "lon": ""}, {"parcel_id": "289085", "address": "", "lat": "", "lon": ""}, {"parcel_id": "289091", "address": "", "lat": "", "lon": ""}, {"parcel_id": "290056", "address": "", "lat": "", "lon": ""}, {"parcel_id": "290058", "address": "", "lat": "", "lon": ""}, {"parcel_id": "290548", "address": "", "lat": "", "lon": ""}, {"parcel_id": "290561", "address": "", "lat": "", "lon": ""}, {"parcel_id": "291016", "address": "", "lat": "", "lon": ""}, {"parcel_id": "291019", "address": "", "lat": "", "lon": ""}, {"parcel_id": "291021", "address": "", "lat": "", "lon": ""}, {"parcel_id": "291536", "address": "", "lat": "", "lon": ""}, {"parcel_id": "416588", "address": "7612 PORTER HOUSE DR", "lat": "36.023719", "lon": "-86.71156"}]}