{"cluster_id": 6092, "name": "COPPERLINE RANCH AGRICENTER LLC", "entity_count": 1, "parcel_count": 2, "total_market_value": 720700, "total_acres": 6.5, "owner_names": ["COPPERLINE RANCH AGRICENTER LLC"], "registered_agents": [], "principal_offices": [], "primary_sos_status": "", "primary_foreign_state": "", "brand": "", "opencorporates": "https://opencorporates.com/companies?q=COPPERLINE+RANCH+AGRICENTER+LLC&utf8=%E2%9C%93", "primary_type": "", "portfolio": {"n_parcels_with_acs": 2, "median_income": 80583, "median_home_value": 441500, "pct_renter": 46, "pct_poverty": null, "pct_vacant": 12, "pct_black": 13, "pct_white": 70, "pct_hispanic": 15, "pct_asian": 0}, "related": [], "parcels": [{"parcel_id": "110250", "address": "3163 BRANDAU RD", "lat": "36.176769", "lon": "-86.626001", "sale_price": -1.0, "sale_date": "", "market_value": 389000.0, "beds": 2.0, "bath": 1.0, "sqft": 756.0, "year_built": "1940", "acres": 6.46}, {"parcel_id": "394806", "address": "3165 BRANDAU RD", "lat": "36.177392", "lon": "-86.625206", "sale_price": -1.0, "sale_date": "", "market_value": 331700.0, "beds": 2.0, "bath": 1.0, "sqft": 624.0, "year_built": "1961", "acres": null}]}