{"cluster_id": 631, "name": "RED GROUP LLC", "entity_count": 3, "parcel_count": 17, "total_market_value": 0, "total_acres": 0.0, "owner_names": ["R J YORK HOMES LLC", "RED GROUP LLC", "YORK CONSTRUCTION LLC"], "registered_agents": [], "principal_offices": [], "primary_sos_status": "", "primary_foreign_state": "", "brand": "", "opencorporates": "https://opencorporates.com/companies?q=RED+GROUP+LLC&utf8=%E2%9C%93", "primary_type": "", "portfolio": {"n_parcels_with_acs": 2, "median_income": 76969, "median_home_value": 349950, "pct_renter": 24, "pct_poverty": null, "pct_vacant": 15, "pct_black": 37, "pct_white": 57, "pct_hispanic": 2, "pct_asian": 0}, "related": [{"owner": "YORK CONSTRUCTION LLC", "parcels": 5, "via": "mailing address"}, {"owner": "R J YORK HOMES LLC", "parcels": 4, "via": "mailing address"}], "parcels": [{"parcel_id": "102680", "address": "", "lat": "", "lon": ""}, {"parcel_id": "166021", "address": "", "lat": "", "lon": ""}, {"parcel_id": "249762", "address": "", "lat": "", "lon": ""}, {"parcel_id": "252879", "address": "", "lat": "", "lon": ""}, {"parcel_id": "259992", "address": "", "lat": "", "lon": ""}, {"parcel_id": "284468", "address": "", "lat": "", "lon": ""}, {"parcel_id": "284469", "address": "", "lat": "", "lon": ""}, {"parcel_id": "284471", "address": "", "lat": "", "lon": ""}, {"parcel_id": "385070", "address": "1382 RURAL HILL RD UNIT 341", "lat": "36.054974", "lon": "-86.650392"}, {"parcel_id": "42939", "address": "", "lat": "", "lon": ""}, {"parcel_id": "454201", "address": "0 TWIN FALLS DR", "lat": "36.327151", "lon": "-86.875656"}, {"parcel_id": "76215", "address": "", "lat": "", "lon": ""}, {"parcel_id": "92281", "address": "", "lat": "", "lon": ""}, {"parcel_id": "92282", "address": "", "lat": "", "lon": ""}, {"parcel_id": "93334", "address": "", "lat": "", "lon": ""}, {"parcel_id": "93335", "address": "", "lat": "", "lon": ""}, {"parcel_id": "93336", "address": "", "lat": "", "lon": ""}]}