{"cluster_id": 7550, "name": "NGC 891 TRUST", "entity_count": 1, "parcel_count": 2, "total_market_value": 2618000, "total_acres": 0.3, "owner_names": ["NGC 891 TRUST"], "registered_agents": [], "principal_offices": [], "primary_sos_status": "", "primary_foreign_state": "", "brand": "", "opencorporates": "https://opencorporates.com/companies?q=NGC+891+TRUST&utf8=%E2%9C%93", "primary_type": "", "portfolio": {"n_parcels_with_acs": 2, "median_income": 56581, "median_home_value": null, "pct_renter": 99, "pct_poverty": null, "pct_vacant": 4, "pct_black": 30, "pct_white": 51, "pct_hispanic": 9, "pct_asian": 0}, "related": [], "parcels": [{"parcel_id": "100303", "address": "205 S 6TH ST", "lat": "36.171075", "lon": "-86.761651", "sale_price": 320400.0, "sale_date": "14 Jul 2017", "market_value": 743800.0, "beds": 2.0, "bath": 1.0, "sqft": 1261.0, "year_built": "1975", "acres": 0.11}, {"parcel_id": "99933", "address": "600 RUSSELL ST", "lat": "36.171373", "lon": "-86.761902", "sale_price": 640000.0, "sale_date": "30 Apr 2013", "market_value": 1874200.0, "beds": 4.0, "bath": 4.0, "sqft": 3882.0, "year_built": "1995", "acres": 0.21}]}