{"cluster_id": 8054, "name": "RUMANS LIVING TRUST THE", "entity_count": 2, "parcel_count": 2, "total_market_value": 1609100, "total_acres": 1.1, "owner_names": ["RUMANS LIVING TRUST", "RUMANS LIVING TRUST THE"], "registered_agents": [], "principal_offices": [], "primary_sos_status": "", "primary_foreign_state": "", "brand": "", "opencorporates": "https://opencorporates.com/companies?q=RUMANS+LIVING+TRUST+THE&utf8=%E2%9C%93", "primary_type": "", "portfolio": {"n_parcels_with_acs": 2, "median_income": 132644, "median_home_value": 500700, "pct_renter": 18, "pct_poverty": null, "pct_vacant": 0, "pct_black": 3, "pct_white": 93, "pct_hispanic": 6, "pct_asian": 0}, "related": [{"owner": "RUMANS LIVING TRUST", "parcels": 1, "via": "mailing address"}], "parcels": [{"parcel_id": "238926", "address": "5013 MAYWOOD DR", "lat": "36.070625", "lon": "-86.75745", "sale_price": 385000.0, "sale_date": "1 Jun 2017", "market_value": 686500.0, "beds": 2.0, "bath": 1.0, "sqft": 1864.0, "year_built": "1985", "acres": 0.48}, {"parcel_id": "271225", "address": "5405 WAKEFIELD DR", "lat": "36.050413", "lon": "-86.747607", "sale_price": 1000000.0, "sale_date": "17 May 2022", "market_value": 922600.0, "beds": 4.0, "bath": 3.0, "sqft": 2088.0, "year_built": "2005", "acres": 0.61}]}