{"cluster_id": 8377, "name": "THE PEACOCK COMMUNITY PROPERTY TRUST", "entity_count": 1, "parcel_count": 2, "total_market_value": 6139600, "total_acres": 1.1, "owner_names": ["THE PEACOCK COMMUNITY PROPERTY TRUST"], "registered_agents": [], "principal_offices": [], "primary_sos_status": "", "primary_foreign_state": "", "brand": "", "opencorporates": "https://opencorporates.com/companies?q=THE+PEACOCK+COMMUNITY+PROPERTY+TRUST&utf8=%E2%9C%93", "primary_type": "", "portfolio": {"n_parcels_with_acs": 2, "median_income": 185715, "median_home_value": 1316600, "pct_renter": 40, "pct_poverty": null, "pct_vacant": 9, "pct_black": 2, "pct_white": 87, "pct_hispanic": 1, "pct_asian": 2}, "related": [], "parcels": [{"parcel_id": "209180", "address": "4508 HARPETH HILLS DR", "lat": "36.089174", "lon": "-86.849205", "sale_price": -1.0, "sale_date": "", "market_value": 4959100.0, "beds": 4.0, "bath": 5.0, "sqft": 6227.0, "year_built": "2007", "acres": 1.07}, {"parcel_id": "385630", "address": "301 DEMONBREUN ST UNIT 1003", "lat": "36.159256", "lon": "-86.774953", "sale_price": 526000.0, "sale_date": "15 Dec 2014", "market_value": 1180500.0, "beds": 2.0, "bath": 2.0, "sqft": 1080.0, "year_built": "2008", "acres": null}]}